Memoria/probador_memoria.v
//Proyecto II
//Desarrollo de Memoria
//5-11-2012
//Version 1.0

//Probador

module probador_memoria #(
            parameter DATA_WIDTH=8, //tamaño de datos FIFO_data_in
            parameter ADDR_WIDTH=8)  //tamaño de direcciones
                    
(output reg [(DATA_WIDTH-1):0] FIFO_data_in,  //entrada FIFO_data_in 
  output reg[(ADDR_WIDTH-1):0] wr_ptr,  //direccíón de escritura
  output reg[(ADDR_WIDTH-1):0] rd_ptr,  //direccíón de lectura
  output reg clk,   //señal de reloj
  output reg write_enable, //enable
  output reg read_enable, //enable
  input [(DATA_WIDTH-1):0] FIFO_data_out //salida FIFO_data_out
);
    initial begin
        FIFO_data_in <= 0;
        wr_ptr <= 0;
        rd_ptr <= 0;
        clk <= 0;
        write_enable <= 0;
        read_enable <= 0;
    end
    always #1 clk <= ~clk;

	initial begin
	$dumpfile("memoria.vcd");
	$dumpvars;

    @(posedge clk);
    write_enable <= 1;
    read_enable <= 1;
    @(posedge clk);
    FIFO_data_in <= 8'hFF;
    wr_ptr <= 8'h01;
    rd_ptr <= 8'h00;
    

    @(posedge clk);
    FIFO_data_in <= 8'hAF;
    wr_ptr <= 8'h05;
    rd_ptr <= 8'h00;

    @(posedge clk);
    FIFO_data_in <= 8'h17;
    wr_ptr <= 8'h06;
    rd_ptr <= 8'h01;

    @(posedge clk);
    FIFO_data_in <= 8'hB8;
    wr_ptr <= 8'h5C;
    rd_ptr <= 8'h05;

    @(posedge clk);
    FIFO_data_in <= 8'h6A;
    wr_ptr <= 8'h9F;
    rd_ptr <= 8'h06;

	#3 $finish;
    
	end

endmodule

Memoria/memoria_synth.v
/* Generated by Yosys 0.9 (git sha1 1979e0b) */

(* dynports =  1  *)
(* top =  1  *)
(* src = "memoria_synth.v:8" *)
module memoria_synth(FIFO_data_in, wr_ptr, rd_ptr, clk, write_enable, read_enable, FIFO_data_out_synth);
  (* src = "memoria_synth.v:23" *)
  (* unused_bits = "3 4 5 6 7" *)
  wire [7:0] _000_;
  (* src = "memoria_synth.v:23" *)
  wire [7:0] _001_;
  wire _002_;
  wire _003_;
  wire _004_;
  wire _005_;
  wire _006_;
  wire _007_;
  wire _008_;
  wire _009_;
  wire _010_;
  wire _011_;
  wire _012_;
  wire _013_;
  wire _014_;
  wire _015_;
  wire _016_;
  wire [7:0] _017_;
  wire [7:0] _018_;
  wire [7:0] _019_;
  wire [7:0] _020_;
  wire [7:0] _021_;
  wire [7:0] _022_;
  wire [7:0] _023_;
  wire [7:0] _024_;
  wire _025_;
  wire _026_;
  wire _027_;
  wire _028_;
  wire _029_;
  wire _030_;
  wire _031_;
  wire _032_;
  wire [7:0] _033_;
  wire [7:0] _034_;
  wire [7:0] _035_;
  wire [7:0] _036_;
  wire [7:0] _037_;
  wire [7:0] _038_;
  wire [7:0] _039_;
  wire [7:0] _040_;
  (* src = "memoria_synth.v:12" *)
  input [7:0] FIFO_data_in;
  (* src = "memoria_synth.v:18" *)
  output [7:0] FIFO_data_out_synth;
  reg [7:0] FIFO_data_out_synth;
  (* src = "memoria_synth.v:15" *)
  input clk;
  reg [7:0] \ram[0] ;
  reg [7:0] \ram[1] ;
  reg [7:0] \ram[2] ;
  reg [7:0] \ram[3] ;
  reg [7:0] \ram[4] ;
  reg [7:0] \ram[5] ;
  reg [7:0] \ram[6] ;
  reg [7:0] \ram[7] ;
  (* src = "memoria_synth.v:14" *)
  input [7:0] rd_ptr;
  (* src = "memoria_synth.v:17" *)
  input read_enable;
  (* src = "memoria_synth.v:13" *)
  input [7:0] wr_ptr;
  (* src = "memoria_synth.v:16" *)
  input write_enable;
  assign _000_[0] = write_enable ? (* src = "memoria_synth.v:24" *) wr_ptr[0] : 1'hx;
  assign _000_[1] = write_enable ? (* src = "memoria_synth.v:24" *) wr_ptr[1] : 1'hx;
  assign _000_[2] = write_enable ? (* src = "memoria_synth.v:24" *) wr_ptr[2] : 1'hx;
  assign _001_[0] = write_enable ? (* src = "memoria_synth.v:24" *) FIFO_data_in[0] : 1'hx;
  assign _001_[1] = write_enable ? (* src = "memoria_synth.v:24" *) FIFO_data_in[1] : 1'hx;
  assign _001_[2] = write_enable ? (* src = "memoria_synth.v:24" *) FIFO_data_in[2] : 1'hx;
  assign _001_[3] = write_enable ? (* src = "memoria_synth.v:24" *) FIFO_data_in[3] : 1'hx;
  assign _001_[4] = write_enable ? (* src = "memoria_synth.v:24" *) FIFO_data_in[4] : 1'hx;
  assign _001_[5] = write_enable ? (* src = "memoria_synth.v:24" *) FIFO_data_in[5] : 1'hx;
  assign _001_[6] = write_enable ? (* src = "memoria_synth.v:24" *) FIFO_data_in[6] : 1'hx;
  assign _001_[7] = write_enable ? (* src = "memoria_synth.v:24" *) FIFO_data_in[7] : 1'hx;
  assign _017_[0] = read_enable ? _024_[0] : FIFO_data_out_synth[0];
  assign _017_[1] = read_enable ? _024_[1] : FIFO_data_out_synth[1];
  assign _017_[2] = read_enable ? _024_[2] : FIFO_data_out_synth[2];
  assign _017_[3] = read_enable ? _024_[3] : FIFO_data_out_synth[3];
  assign _017_[4] = read_enable ? _024_[4] : FIFO_data_out_synth[4];
  assign _017_[5] = read_enable ? _024_[5] : FIFO_data_out_synth[5];
  assign _017_[6] = read_enable ? _024_[6] : FIFO_data_out_synth[6];
  assign _017_[7] = read_enable ? _024_[7] : FIFO_data_out_synth[7];
  assign _024_[0] = rd_ptr[2] ? _019_[0] : _018_[0];
  assign _024_[1] = rd_ptr[2] ? _019_[1] : _018_[1];
  assign _024_[2] = rd_ptr[2] ? _019_[2] : _018_[2];
  assign _024_[3] = rd_ptr[2] ? _019_[3] : _018_[3];
  assign _024_[4] = rd_ptr[2] ? _019_[4] : _018_[4];
  assign _024_[5] = rd_ptr[2] ? _019_[5] : _018_[5];
  assign _024_[6] = rd_ptr[2] ? _019_[6] : _018_[6];
  assign _024_[7] = rd_ptr[2] ? _019_[7] : _018_[7];
  assign _018_[0] = rd_ptr[1] ? _021_[0] : _020_[0];
  assign _018_[1] = rd_ptr[1] ? _021_[1] : _020_[1];
  assign _018_[2] = rd_ptr[1] ? _021_[2] : _020_[2];
  assign _018_[3] = rd_ptr[1] ? _021_[3] : _020_[3];
  assign _018_[4] = rd_ptr[1] ? _021_[4] : _020_[4];
  assign _018_[5] = rd_ptr[1] ? _021_[5] : _020_[5];
  assign _018_[6] = rd_ptr[1] ? _021_[6] : _020_[6];
  assign _018_[7] = rd_ptr[1] ? _021_[7] : _020_[7];
  assign _019_[0] = rd_ptr[1] ? _023_[0] : _022_[0];
  assign _019_[1] = rd_ptr[1] ? _023_[1] : _022_[1];
  assign _019_[2] = rd_ptr[1] ? _023_[2] : _022_[2];
  assign _019_[3] = rd_ptr[1] ? _023_[3] : _022_[3];
  assign _019_[4] = rd_ptr[1] ? _023_[4] : _022_[4];
  assign _019_[5] = rd_ptr[1] ? _023_[5] : _022_[5];
  assign _019_[6] = rd_ptr[1] ? _023_[6] : _022_[6];
  assign _019_[7] = rd_ptr[1] ? _023_[7] : _022_[7];
  assign _020_[0] = rd_ptr[0] ? \ram[1] [0] : \ram[0] [0];
  assign _020_[1] = rd_ptr[0] ? \ram[1] [1] : \ram[0] [1];
  assign _020_[2] = rd_ptr[0] ? \ram[1] [2] : \ram[0] [2];
  assign _020_[3] = rd_ptr[0] ? \ram[1] [3] : \ram[0] [3];
  assign _020_[4] = rd_ptr[0] ? \ram[1] [4] : \ram[0] [4];
  assign _020_[5] = rd_ptr[0] ? \ram[1] [5] : \ram[0] [5];
  assign _020_[6] = rd_ptr[0] ? \ram[1] [6] : \ram[0] [6];
  assign _020_[7] = rd_ptr[0] ? \ram[1] [7] : \ram[0] [7];
  assign _021_[0] = rd_ptr[0] ? \ram[3] [0] : \ram[2] [0];
  assign _021_[1] = rd_ptr[0] ? \ram[3] [1] : \ram[2] [1];
  assign _021_[2] = rd_ptr[0] ? \ram[3] [2] : \ram[2] [2];
  assign _021_[3] = rd_ptr[0] ? \ram[3] [3] : \ram[2] [3];
  assign _021_[4] = rd_ptr[0] ? \ram[3] [4] : \ram[2] [4];
  assign _021_[5] = rd_ptr[0] ? \ram[3] [5] : \ram[2] [5];
  assign _021_[6] = rd_ptr[0] ? \ram[3] [6] : \ram[2] [6];
  assign _021_[7] = rd_ptr[0] ? \ram[3] [7] : \ram[2] [7];
  assign _022_[0] = rd_ptr[0] ? \ram[5] [0] : \ram[4] [0];
  assign _022_[1] = rd_ptr[0] ? \ram[5] [1] : \ram[4] [1];
  assign _022_[2] = rd_ptr[0] ? \ram[5] [2] : \ram[4] [2];
  assign _022_[3] = rd_ptr[0] ? \ram[5] [3] : \ram[4] [3];
  assign _022_[4] = rd_ptr[0] ? \ram[5] [4] : \ram[4] [4];
  assign _022_[5] = rd_ptr[0] ? \ram[5] [5] : \ram[4] [5];
  assign _022_[6] = rd_ptr[0] ? \ram[5] [6] : \ram[4] [6];
  assign _022_[7] = rd_ptr[0] ? \ram[5] [7] : \ram[4] [7];
  assign _023_[0] = rd_ptr[0] ? \ram[7] [0] : \ram[6] [0];
  assign _023_[1] = rd_ptr[0] ? \ram[7] [1] : \ram[6] [1];
  assign _023_[2] = rd_ptr[0] ? \ram[7] [2] : \ram[6] [2];
  assign _023_[3] = rd_ptr[0] ? \ram[7] [3] : \ram[6] [3];
  assign _023_[4] = rd_ptr[0] ? \ram[7] [4] : \ram[6] [4];
  assign _023_[5] = rd_ptr[0] ? \ram[7] [5] : \ram[6] [5];
  assign _023_[6] = rd_ptr[0] ? \ram[7] [6] : \ram[6] [6];
  assign _023_[7] = rd_ptr[0] ? \ram[7] [7] : \ram[6] [7];
  assign _033_[0] = _025_ ? _001_[0] : \ram[0] [0];
  assign _033_[1] = _025_ ? _001_[1] : \ram[0] [1];
  assign _033_[2] = _025_ ? _001_[2] : \ram[0] [2];
  assign _033_[3] = _025_ ? _001_[3] : \ram[0] [3];
  assign _033_[4] = _025_ ? _001_[4] : \ram[0] [4];
  assign _033_[5] = _025_ ? _001_[5] : \ram[0] [5];
  assign _033_[6] = _025_ ? _001_[6] : \ram[0] [6];
  assign _033_[7] = _025_ ? _001_[7] : \ram[0] [7];
  assign _034_[0] = _026_ ? _001_[0] : \ram[1] [0];
  assign _034_[1] = _026_ ? _001_[1] : \ram[1] [1];
  assign _034_[2] = _026_ ? _001_[2] : \ram[1] [2];
  assign _034_[3] = _026_ ? _001_[3] : \ram[1] [3];
  assign _034_[4] = _026_ ? _001_[4] : \ram[1] [4];
  assign _034_[5] = _026_ ? _001_[5] : \ram[1] [5];
  assign _034_[6] = _026_ ? _001_[6] : \ram[1] [6];
  assign _034_[7] = _026_ ? _001_[7] : \ram[1] [7];
  assign _035_[0] = _027_ ? _001_[0] : \ram[2] [0];
  assign _035_[1] = _027_ ? _001_[1] : \ram[2] [1];
  assign _035_[2] = _027_ ? _001_[2] : \ram[2] [2];
  assign _035_[3] = _027_ ? _001_[3] : \ram[2] [3];
  assign _035_[4] = _027_ ? _001_[4] : \ram[2] [4];
  assign _035_[5] = _027_ ? _001_[5] : \ram[2] [5];
  assign _035_[6] = _027_ ? _001_[6] : \ram[2] [6];
  assign _035_[7] = _027_ ? _001_[7] : \ram[2] [7];
  assign _036_[0] = _028_ ? _001_[0] : \ram[3] [0];
  assign _036_[1] = _028_ ? _001_[1] : \ram[3] [1];
  assign _036_[2] = _028_ ? _001_[2] : \ram[3] [2];
  assign _036_[3] = _028_ ? _001_[3] : \ram[3] [3];
  assign _036_[4] = _028_ ? _001_[4] : \ram[3] [4];
  assign _036_[5] = _028_ ? _001_[5] : \ram[3] [5];
  assign _036_[6] = _028_ ? _001_[6] : \ram[3] [6];
  assign _036_[7] = _028_ ? _001_[7] : \ram[3] [7];
  assign _037_[0] = _029_ ? _001_[0] : \ram[4] [0];
  assign _037_[1] = _029_ ? _001_[1] : \ram[4] [1];
  assign _037_[2] = _029_ ? _001_[2] : \ram[4] [2];
  assign _037_[3] = _029_ ? _001_[3] : \ram[4] [3];
  assign _037_[4] = _029_ ? _001_[4] : \ram[4] [4];
  assign _037_[5] = _029_ ? _001_[5] : \ram[4] [5];
  assign _037_[6] = _029_ ? _001_[6] : \ram[4] [6];
  assign _037_[7] = _029_ ? _001_[7] : \ram[4] [7];
  assign _038_[0] = _030_ ? _001_[0] : \ram[5] [0];
  assign _038_[1] = _030_ ? _001_[1] : \ram[5] [1];
  assign _038_[2] = _030_ ? _001_[2] : \ram[5] [2];
  assign _038_[3] = _030_ ? _001_[3] : \ram[5] [3];
  assign _038_[4] = _030_ ? _001_[4] : \ram[5] [4];
  assign _038_[5] = _030_ ? _001_[5] : \ram[5] [5];
  assign _038_[6] = _030_ ? _001_[6] : \ram[5] [6];
  assign _038_[7] = _030_ ? _001_[7] : \ram[5] [7];
  assign _039_[0] = _031_ ? _001_[0] : \ram[6] [0];
  assign _039_[1] = _031_ ? _001_[1] : \ram[6] [1];
  assign _039_[2] = _031_ ? _001_[2] : \ram[6] [2];
  assign _039_[3] = _031_ ? _001_[3] : \ram[6] [3];
  assign _039_[4] = _031_ ? _001_[4] : \ram[6] [4];
  assign _039_[5] = _031_ ? _001_[5] : \ram[6] [5];
  assign _039_[6] = _031_ ? _001_[6] : \ram[6] [6];
  assign _039_[7] = _031_ ? _001_[7] : \ram[6] [7];
  assign _040_[0] = _032_ ? _001_[0] : \ram[7] [0];
  assign _040_[1] = _032_ ? _001_[1] : \ram[7] [1];
  assign _040_[2] = _032_ ? _001_[2] : \ram[7] [2];
  assign _040_[3] = _032_ ? _001_[3] : \ram[7] [3];
  assign _040_[4] = _032_ ? _001_[4] : \ram[7] [4];
  assign _040_[5] = _032_ ? _001_[5] : \ram[7] [5];
  assign _040_[6] = _032_ ? _001_[6] : \ram[7] [6];
  assign _040_[7] = _032_ ? _001_[7] : \ram[7] [7];
  assign _014_ = ~_000_[0];
  assign _015_ = ~_000_[1];
  assign _016_ = ~_000_[2];
  always @(posedge clk)
      \ram[4] [0] <= _037_[0];
  always @(posedge clk)
      \ram[4] [1] <= _037_[1];
  always @(posedge clk)
      \ram[4] [2] <= _037_[2];
  always @(posedge clk)
      \ram[4] [3] <= _037_[3];
  always @(posedge clk)
      \ram[4] [4] <= _037_[4];
  always @(posedge clk)
      \ram[4] [5] <= _037_[5];
  always @(posedge clk)
      \ram[4] [6] <= _037_[6];
  always @(posedge clk)
      \ram[4] [7] <= _037_[7];
  always @(posedge clk)
      \ram[2] [0] <= _035_[0];
  always @(posedge clk)
      \ram[2] [1] <= _035_[1];
  always @(posedge clk)
      \ram[2] [2] <= _035_[2];
  always @(posedge clk)
      \ram[2] [3] <= _035_[3];
  always @(posedge clk)
      \ram[2] [4] <= _035_[4];
  always @(posedge clk)
      \ram[2] [5] <= _035_[5];
  always @(posedge clk)
      \ram[2] [6] <= _035_[6];
  always @(posedge clk)
      \ram[2] [7] <= _035_[7];
  always @(posedge clk)
      \ram[0] [0] <= _033_[0];
  always @(posedge clk)
      \ram[0] [1] <= _033_[1];
  always @(posedge clk)
      \ram[0] [2] <= _033_[2];
  always @(posedge clk)
      \ram[0] [3] <= _033_[3];
  always @(posedge clk)
      \ram[0] [4] <= _033_[4];
  always @(posedge clk)
      \ram[0] [5] <= _033_[5];
  always @(posedge clk)
      \ram[0] [6] <= _033_[6];
  always @(posedge clk)
      \ram[0] [7] <= _033_[7];
  always @(posedge clk)
      \ram[5] [0] <= _038_[0];
  always @(posedge clk)
      \ram[5] [1] <= _038_[1];
  always @(posedge clk)
      \ram[5] [2] <= _038_[2];
  always @(posedge clk)
      \ram[5] [3] <= _038_[3];
  always @(posedge clk)
      \ram[5] [4] <= _038_[4];
  always @(posedge clk)
      \ram[5] [5] <= _038_[5];
  always @(posedge clk)
      \ram[5] [6] <= _038_[6];
  always @(posedge clk)
      \ram[5] [7] <= _038_[7];
  always @(posedge clk)
      \ram[1] [0] <= _034_[0];
  always @(posedge clk)
      \ram[1] [1] <= _034_[1];
  always @(posedge clk)
      \ram[1] [2] <= _034_[2];
  always @(posedge clk)
      \ram[1] [3] <= _034_[3];
  always @(posedge clk)
      \ram[1] [4] <= _034_[4];
  always @(posedge clk)
      \ram[1] [5] <= _034_[5];
  always @(posedge clk)
      \ram[1] [6] <= _034_[6];
  always @(posedge clk)
      \ram[1] [7] <= _034_[7];
  always @(posedge clk)
      \ram[3] [0] <= _036_[0];
  always @(posedge clk)
      \ram[3] [1] <= _036_[1];
  always @(posedge clk)
      \ram[3] [2] <= _036_[2];
  always @(posedge clk)
      \ram[3] [3] <= _036_[3];
  always @(posedge clk)
      \ram[3] [4] <= _036_[4];
  always @(posedge clk)
      \ram[3] [5] <= _036_[5];
  always @(posedge clk)
      \ram[3] [6] <= _036_[6];
  always @(posedge clk)
      \ram[3] [7] <= _036_[7];
  always @(posedge clk)
      \ram[6] [0] <= _039_[0];
  always @(posedge clk)
      \ram[6] [1] <= _039_[1];
  always @(posedge clk)
      \ram[6] [2] <= _039_[2];
  always @(posedge clk)
      \ram[6] [3] <= _039_[3];
  always @(posedge clk)
      \ram[6] [4] <= _039_[4];
  always @(posedge clk)
      \ram[6] [5] <= _039_[5];
  always @(posedge clk)
      \ram[6] [6] <= _039_[6];
  always @(posedge clk)
      \ram[6] [7] <= _039_[7];
  always @(posedge clk)
      \ram[7] [0] <= _040_[0];
  always @(posedge clk)
      \ram[7] [1] <= _040_[1];
  always @(posedge clk)
      \ram[7] [2] <= _040_[2];
  always @(posedge clk)
      \ram[7] [3] <= _040_[3];
  always @(posedge clk)
      \ram[7] [4] <= _040_[4];
  always @(posedge clk)
      \ram[7] [5] <= _040_[5];
  always @(posedge clk)
      \ram[7] [6] <= _040_[6];
  always @(posedge clk)
      \ram[7] [7] <= _040_[7];
  always @(posedge clk)
      FIFO_data_out_synth[0] <= _017_[0];
  always @(posedge clk)
      FIFO_data_out_synth[1] <= _017_[1];
  always @(posedge clk)
      FIFO_data_out_synth[2] <= _017_[2];
  always @(posedge clk)
      FIFO_data_out_synth[3] <= _017_[3];
  always @(posedge clk)
      FIFO_data_out_synth[4] <= _017_[4];
  always @(posedge clk)
      FIFO_data_out_synth[5] <= _017_[5];
  always @(posedge clk)
      FIFO_data_out_synth[6] <= _017_[6];
  always @(posedge clk)
      FIFO_data_out_synth[7] <= _017_[7];
  assign _008_ = _015_ & _016_;
  assign _009_ = _014_ & _008_;
  assign _025_ = _009_ & write_enable;
  assign _010_ = _000_[0] & _008_;
  assign _026_ = _010_ & write_enable;
  assign _011_ = _000_[1] & _016_;
  assign _012_ = _014_ & _011_;
  assign _027_ = _012_ & write_enable;
  assign _013_ = _000_[0] & _011_;
  assign _028_ = _013_ & write_enable;
  assign _002_ = _015_ & _000_[2];
  assign _003_ = _014_ & _002_;
  assign _029_ = _003_ & write_enable;
  assign _004_ = _000_[0] & _002_;
  assign _030_ = _004_ & write_enable;
  assign _005_ = _000_[1] & _000_[2];
  assign _006_ = _014_ & _005_;
  assign _031_ = _006_ & write_enable;
  assign _007_ = _000_[0] & _005_;
  assign _032_ = _007_ & write_enable;
endmodule

Memoria/memoria.v
//Proyecto II
//Desarrollo de Memoria
//5-11-2012
//Version 1.0
//Modulo tomado de: https://riptutorial.com/verilog/example/10519/single-port-synchronous-ram
//Tambien de: https://yamin.cis.k.hosei.ac.jp/fpga/verilog-memory.html

module memoria #(
  parameter DATA_WIDTH=8, //tamaño de datos FIFO_data_in
  parameter ADDR_WIDTH=8)  //tamaño de direcciones

(input [(DATA_WIDTH-1):0] FIFO_data_in, //entrada FIFO_data_in 
  input [(ADDR_WIDTH-1):0] wr_ptr, //direccíón de escritura
  input [(ADDR_WIDTH-1):0] rd_ptr, //direccíón de lectura
  input clk, //señal de reloj
  input write_enable,
  input read_enable,
  output reg [(DATA_WIDTH-1):0] FIFO_data_out //salida FIFO_data_out
);

  reg [DATA_WIDTH-1:0] ram [0:ADDR_WIDTH-1]; //Tamaño de la memoria

  always @(posedge clk) begin 
        if (write_enable) ram[wr_ptr] <= FIFO_data_in; //Escritura
        if (read_enable) FIFO_data_out <= ram[rd_ptr]; //Lectura
      end
  
endmodule

Memoria/banco_memoria.v
//Proyecto II
//Desarrollo de Memoria
//5-11-2012
//Version 1.0

//Banco de pruebas para memoria

// escala	unidad temporal (valor de "#1") / precisión
`timescale 	1ns	/ 100ps

// Se incluyen los archivos necesario
`include "memoria.v"
`include "memoria_synth.v"
`include "probador_memoria.v"

module banco #(
  parameter DATA_WIDTH=8, //tamaño de datos FIFO_data_in
  parameter ADDR_WIDTH=8);  //tamaño de direcciones

    //Wires
    wire [(DATA_WIDTH-1):0] FIFO_data_in; //tamaño de datos FIFO_data_in
    wire [(ADDR_WIDTH-1):0] wr_ptr; //direccíón de escritura
    wire [(ADDR_WIDTH-1):0] rd_ptr; //direccíón de lectura
    wire clk; //señal de reloj
	wire write_enable; //señal de reloj
	wire read_enable; //señal de reloj
    wire [(DATA_WIDTH-1):0] FIFO_data_out; //salida FIFO_data_out
    wire [(DATA_WIDTH-1):0] FIFO_data_out_synth; //salida FIFO_data_out

	// Se instancia el módulo de memoria conductual
	memoria conductual(/*AUTOINST*/
			   // Outputs
			   .FIFO_data_out	(FIFO_data_out[(DATA_WIDTH-1):0]),
			   // Inputs
			   .FIFO_data_in	(FIFO_data_in[(DATA_WIDTH-1):0]),
			   .wr_ptr		(wr_ptr[(ADDR_WIDTH-1):0]),
			   .rd_ptr		(rd_ptr[(ADDR_WIDTH-1):0]),
			   .clk			(clk),
			   .write_enable	(write_enable),
			   .read_enable		(read_enable));

    memoria_synth estructural(/*AUTOINST*/
			      // Outputs
			      .FIFO_data_out_synth(FIFO_data_out_synth[7:0]),
			      // Inputs
			      .FIFO_data_in	(FIFO_data_in[7:0]),
			      .clk		(clk),
			      .rd_ptr		(rd_ptr[7:0]),
			      .read_enable	(read_enable),
			      .wr_ptr		(wr_ptr[7:0]),
			      .write_enable	(write_enable));

	// Probador
	probador_memoria probador(/*AUTOINST*/
				  // Outputs
				  .FIFO_data_in		(FIFO_data_in[(DATA_WIDTH-1):0]),
				  .wr_ptr		(wr_ptr[(ADDR_WIDTH-1):0]),
				  .rd_ptr		(rd_ptr[(ADDR_WIDTH-1):0]),
				  .clk			(clk),
				  .write_enable		(write_enable),
				  .read_enable		(read_enable),
				  // Inputs
				  .FIFO_data_out	(FIFO_data_out[(DATA_WIDTH-1):0]));

endmodule

Memoria/memoria.vcd
$date
	Tue Nov  9 10:45:32 2021
$end
$version
	Icarus Verilog
$end
$timescale
	100ps
$end
$scope module banco $end
$var wire 1 ! write_enable $end
$var wire 8 " wr_ptr [7:0] $end
$var wire 1 # read_enable $end
$var wire 8 $ rd_ptr [7:0] $end
$var wire 1 % clk $end
$var wire 8 & FIFO_data_out_synth [7:0] $end
$var wire 8 ' FIFO_data_out [7:0] $end
$var wire 8 ( FIFO_data_in [7:0] $end
$scope module conductual $end
$var wire 1 ! write_enable $end
$var wire 8 ) wr_ptr [7:0] $end
$var wire 1 # read_enable $end
$var wire 8 * rd_ptr [7:0] $end
$var wire 1 % clk $end
$var wire 8 + FIFO_data_in [7:0] $end
$var reg 8 , FIFO_data_out [7:0] $end
$upscope $end
$scope module estructural $end
$var wire 1 - _002_ $end
$var wire 1 . _003_ $end
$var wire 1 / _004_ $end
$var wire 1 0 _005_ $end
$var wire 1 1 _006_ $end
$var wire 1 2 _007_ $end
$var wire 1 3 _008_ $end
$var wire 1 4 _009_ $end
$var wire 1 5 _010_ $end
$var wire 1 6 _011_ $end
$var wire 1 7 _012_ $end
$var wire 1 8 _013_ $end
$var wire 1 9 _014_ $end
$var wire 1 : _015_ $end
$var wire 1 ; _016_ $end
$var wire 1 < _025_ $end
$var wire 1 = _026_ $end
$var wire 1 > _027_ $end
$var wire 1 ? _028_ $end
$var wire 1 @ _029_ $end
$var wire 1 A _030_ $end
$var wire 1 B _031_ $end
$var wire 1 C _032_ $end
$var wire 1 ! write_enable $end
$var wire 8 D wr_ptr [7:0] $end
$var wire 1 # read_enable $end
$var wire 8 E rd_ptr [7:0] $end
$var wire 1 % clk $end
$var wire 8 F _040_ [7:0] $end
$var wire 8 G _039_ [7:0] $end
$var wire 8 H _038_ [7:0] $end
$var wire 8 I _037_ [7:0] $end
$var wire 8 J _036_ [7:0] $end
$var wire 8 K _035_ [7:0] $end
$var wire 8 L _034_ [7:0] $end
$var wire 8 M _033_ [7:0] $end
$var wire 8 N _024_ [7:0] $end
$var wire 8 O _023_ [7:0] $end
$var wire 8 P _022_ [7:0] $end
$var wire 8 Q _021_ [7:0] $end
$var wire 8 R _020_ [7:0] $end
$var wire 8 S _019_ [7:0] $end
$var wire 8 T _018_ [7:0] $end
$var wire 8 U _017_ [7:0] $end
$var wire 8 V _001_ [7:0] $end
$var wire 8 W _000_ [7:0] $end
$var wire 8 X FIFO_data_in [7:0] $end
$var reg 8 Y FIFO_data_out_synth [7:0] $end
$var reg 8 Z \ram[0] [7:0] $end
$var reg 8 [ \ram[1] [7:0] $end
$var reg 8 \ \ram[2] [7:0] $end
$var reg 8 ] \ram[3] [7:0] $end
$var reg 8 ^ \ram[4] [7:0] $end
$var reg 8 _ \ram[5] [7:0] $end
$var reg 8 ` \ram[6] [7:0] $end
$var reg 8 a \ram[7] [7:0] $end
$upscope $end
$scope module probador $end
$var wire 8 b FIFO_data_out [7:0] $end
$var reg 8 c FIFO_data_in [7:0] $end
$var reg 1 % clk $end
$var reg 8 d rd_ptr [7:0] $end
$var reg 1 # read_enable $end
$var reg 8 e wr_ptr [7:0] $end
$var reg 1 ! write_enable $end
$upscope $end
$upscope $end
$enddefinitions $end
#0
$dumpvars
b0 e
b0 d
b0 c
bx b
bx a
bx `
bx _
bx ^
bx ]
bx \
bx [
bx Z
bx Y
b0 X
bzxxx W
bx V
bx U
bx T
bx S
bx R
bx Q
bx P
bx O
bx N
bx M
bx L
bx K
bx J
bx I
bx H
bx G
bx F
b0 E
b0 D
0C
0B
0A
0@
0?
0>
0=
0<
x;
x:
x9
x8
x7
x6
x5
x4
x3
x2
x1
x0
x/
x.
x-
bx ,
b0 +
b0 *
b0 )
b0 (
bx '
bx &
0%
b0 $
0#
b0 "
0!
$end
#10
b0 M
14
13
07
0.
01
0-
1;
00
06
1:
02
0/
08
05
19
b0 V
bz000 W
0C
0B
0A
0@
0?
0>
0=
1<
1#
1!
1%
#20
0%
#30
b0 U
b11111111 L
0<
b0 N
1=
04
15
09
b0 M
b0 T
bz001 W
b11111111 V
b0 R
b1 "
b1 )
b1 D
b1 e
b11111111 (
b11111111 +
b11111111 X
b11111111 c
b0 Z
1%
#40
0%
#50
b10101111 H
0=
1A
05
1/
03
1-
0;
b11111111 L
bz101 W
b10101111 V
b0 '
b0 ,
b0 b
b11111111 [
b0 &
b0 Y
b101 "
b101 )
b101 D
b101 e
b10101111 (
b10101111 +
b10101111 X
b10101111 c
1%
#60
0%
#70
b11111111 U
bx I
b10111 G
b11111111 N
0@
1B
0-
0A
0.
11
b10101111 S
b11111111 T
10
0:
0/
19
b10101111 H
b10101111 P
b11111111 R
bz110 W
b10111 V
b1 $
b1 *
b1 E
b1 d
b110 "
b110 )
b110 D
b110 e
b10111 (
b10111 +
b10111 X
b10111 c
b10101111 _
1%
#80
0%
#90
b10111000 I
1@
0B
1.
01
1-
b10101111 U
00
1:
b10111 G
b10101111 N
bz100 W
b10111000 V
b11111111 '
b11111111 ,
b11111111 b
b10111 `
b11111111 &
b11111111 Y
b101 $
b101 *
b101 E
b101 d
b1011100 "
b1011100 )
b1011100 D
b1011100 e
b10111000 (
b10111000 +
b10111000 X
b10111000 c
1%
#100
0%
#110
b1101010 F
b10111 U
1C
b10101111 H
0@
12
0-
0A
0.
b10111 N
10
0:
0/
09
b10111000 I
b10111 O
b10111000 P
b0 R
b10111 S
bx T
bz111 W
b1101010 V
b110 $
b110 *
b110 E
b110 d
b10011111 "
b10011111 )
b10011111 D
b10011111 e
b1101010 (
b1101010 +
b1101010 X
b1101010 c
b10101111 &
b10101111 Y
b10111000 ^
b10101111 '
b10101111 ,
b10101111 b
1%
#120
0%
#130
b10111 '
b10111 ,
b10111 b
b1101010 a
b10111 &
b10111 Y
1%
