Contadores/probador_contador.v
//Proyecto II
//14-11-2012
//Version 1.0

//Probador

module probador_contador
                    
(output reg clk,   //señal de reloj
  output reg push, //push
  input [5:0]  cuenta,
  input [5:0]  cuenta_synth);

    initial clk <= 0;
    initial push <= 0;
    
    always #1 clk <= ~clk;

	initial begin
	$dumpfile("contador.vcd");
	$dumpvars;

    @(posedge clk);
    @(posedge clk);
    push = 1;
    @(posedge clk);
    @(posedge clk);
    @(posedge clk);
    #0.01 push = 0;
    @(posedge clk);
    @(posedge clk);
    #0.9 push = 1;
    @(posedge clk);
    
    @(posedge clk);
    @(posedge clk);
    @(posedge clk);
    @(posedge clk);
    @(posedge clk);
    @(posedge clk);

	#3 $finish;
    
	end

endmodule

Contadores/contador_synth.v
/* Generated by Yosys 0.9 (git sha1 1979e0b) */

(* top =  1  *)
(* src = "contador_synth.v:6" *)
module contador_synth(push, clk, cuenta);
  (* src = "contador_synth.v:13" *)
  wire [5:0] _00_;
  (* src = "contador_synth.v:15" *)
  (* unused_bits = "6" *)
  wire [31:0] _01_;
  (* src = "contador_synth.v:15|<techmap.v>:260|<techmap.v>:203" *)
  (* unused_bits = "5" *)
  wire [31:0] _02_;
  (* src = "contador_synth.v:15|<techmap.v>:260|<techmap.v>:222" *)
  wire _03_;
  (* src = "contador_synth.v:8" *)
  input clk;
  (* init = 6'h00 *)
  (* src = "contador_synth.v:9" *)
  output [5:0] cuenta;
  reg [5:0] cuenta = 6'h00;
  (* src = "contador_synth.v:7" *)
  input push;
  assign _00_[0] = push ? (* src = "contador_synth.v:15" *) _01_[0] : cuenta[0];
  assign _00_[1] = push ? (* src = "contador_synth.v:15" *) _01_[1] : cuenta[1];
  assign _00_[2] = push ? (* src = "contador_synth.v:15" *) _01_[2] : cuenta[2];
  assign _00_[3] = push ? (* src = "contador_synth.v:15" *) _01_[3] : cuenta[3];
  assign _00_[4] = push ? (* src = "contador_synth.v:15" *) _01_[4] : cuenta[4];
  assign _00_[5] = push ? (* src = "contador_synth.v:15" *) _01_[5] : cuenta[5];
  (* src = "contador_synth.v:13" *)
  always @(posedge clk)
      cuenta[0] <= _00_[0];
  (* src = "contador_synth.v:13" *)
  always @(posedge clk)
      cuenta[1] <= _00_[1];
  (* src = "contador_synth.v:13" *)
  always @(posedge clk)
      cuenta[2] <= _00_[2];
  (* src = "contador_synth.v:13" *)
  always @(posedge clk)
      cuenta[3] <= _00_[3];
  (* src = "contador_synth.v:13" *)
  always @(posedge clk)
      cuenta[4] <= _00_[4];
  (* src = "contador_synth.v:13" *)
  always @(posedge clk)
      cuenta[5] <= _00_[5];
  assign _01_[1] = cuenta[1] ^(* src = "contador_synth.v:15|<techmap.v>:263" *)  cuenta[0];
  assign _01_[2] = cuenta[2] ^(* src = "contador_synth.v:15|<techmap.v>:263" *)  _02_[1];
  assign _01_[3] = cuenta[3] ^(* src = "contador_synth.v:15|<techmap.v>:263" *)  _02_[2];
  assign _01_[4] = cuenta[4] ^(* src = "contador_synth.v:15|<techmap.v>:263" *)  _02_[3];
  assign _01_[5] = cuenta[5] ^(* src = "contador_synth.v:15|<techmap.v>:263" *)  _02_[4];
  assign _01_[0] = cuenta[0] ^(* src = "contador_synth.v:15|<techmap.v>:262" *)  1'h1;
  assign _02_[1] = cuenta[1] &(* src = "contador_synth.v:15|<techmap.v>:260|<techmap.v>:221" *)  cuenta[0];
  assign _02_[3] = _03_ &(* src = "contador_synth.v:15|<techmap.v>:260|<techmap.v>:221" *)  _02_[1];
  assign _03_ = cuenta[3] &(* src = "contador_synth.v:15|<techmap.v>:260|<techmap.v>:222" *)  cuenta[2];
  assign _02_[2] = cuenta[2] &(* src = "contador_synth.v:15|<techmap.v>:260|<techmap.v>:229" *)  _02_[1];
  assign _02_[4] = cuenta[4] &(* src = "contador_synth.v:15|<techmap.v>:260|<techmap.v>:229" *)  _02_[3];
  assign _01_[31:7] = 25'h0000000;
  assign { _02_[31:5], _02_[0] } = { 26'h0000000, _01_[6], cuenta[0] };
endmodule

Contadores/contador.v
//Proyecto II
//13-11-2021
//Version 1
//Modulo de Contadores

module contador 
(input push,
  input clk,
  output reg [5:0] cuenta);

initial cuenta = 3'b000;

always @(posedge clk) begin
    //Por cada push se incrementa la cantidad de datos
  if (push) cuenta <= cuenta + 1;
  else;

end

endmodule

Contadores/banco_contador.v
//Proyecto II
//14-11-2012
//Version 1.0

//Banco de pruebas para contador

// escala	unidad temporal (valor de "#1") / precisión
`timescale 	1ns	/ 100ps

// Se incluyen los archivos necesario
`include "contador.v"
`include "contador_synth.v"
`include "probador_contador.v"

module banco_contador;

    //Wires
    wire clk; //señal de reloj
	wire push; //señal de push
	wire [5:0]  cuenta; //señal de cuenta
    wire [5:0]  cuenta_synth; //señal de cuenta
    
	// Se instancia el módulo de memoria conductual
	contador conductual(/*AUTOINST*/
			    // Outputs
			    .cuenta		(cuenta[5:0] ),
			    // Inputs
			    .push		(push),
			    .clk		(clk));

    contador_synth estructural(/*AUTOINST*/
			       // Outputs
			       .cuenta	(cuenta_synth[5:0]),
			       // Inputs
			       .clk		(clk),
			       .push		(push));

	// Probador
	probador_contador probador(/*AUTOINST*/
				   // Outputs
				   .clk			(clk),
				   .push		(push),
				   // Inputs
				   .cuenta		(cuenta[5:0]),
				   .cuenta_synth	(cuenta_synth[5:0]));

endmodule

Contadores/contador.vcd
$date
	Mon Nov 15 21:58:55 2021
$end
$version
	Icarus Verilog
$end
$timescale
	100ps
$end
$scope module banco_contador $end
$var wire 1 ! push $end
$var wire 6 " cuenta_synth [5:0] $end
$var wire 6 # cuenta [5:0] $end
$var wire 1 $ clk $end
$scope module conductual $end
$var wire 1 ! push $end
$var wire 1 $ clk $end
$var reg 6 % cuenta [5:0] $end
$upscope $end
$scope module estructural $end
$var wire 1 & _03_ $end
$var wire 1 ! push $end
$var wire 1 $ clk $end
$var wire 32 ' _02_ [31:0] $end
$var wire 32 ( _01_ [31:0] $end
$var wire 6 ) _00_ [5:0] $end
$var reg 6 * cuenta [5:0] $end
$upscope $end
$scope module probador $end
$var wire 6 + cuenta [5:0] $end
$var wire 6 , cuenta_synth [5:0] $end
$var reg 1 $ clk $end
$var reg 1 ! push $end
$upscope $end
$upscope $end
$enddefinitions $end
#0
$dumpvars
b0 ,
b0 +
b0 *
b0 )
b0z000001 (
b0z00000 '
0&
b0 %
0$
b0 #
b0 "
0!
$end
#10
1$
#20
0$
#30
b1 )
1!
1$
#40
0$
#50
b10 )
b0z000010 (
b0z00001 '
b1 #
b1 %
b1 +
b1 "
b1 *
b1 ,
1$
#60
0$
#70
b11 )
b0z000011 (
b0z00000 '
b10 "
b10 *
b10 ,
b10 #
b10 %
b10 +
1$
#80
0$
#90
b0z000100 (
b0z00011 '
b11 #
b11 %
b11 +
b11 "
b11 *
b11 ,
b11 )
0!
1$
#100
0$
#110
1$
#120
0$
#130
1$
#139
b100 )
1!
#140
0$
#150
b101 )
b0z000101 (
b0z00000 '
b100 "
b100 *
b100 ,
b100 #
b100 %
b100 +
1$
#160
0$
#170
b110 )
b0z000110 (
b0z00001 '
b101 #
b101 %
b101 +
b101 "
b101 *
b101 ,
1$
#180
0$
#190
b111 )
b0z000111 (
b0z00000 '
b110 "
b110 *
b110 ,
b110 #
b110 %
b110 +
1$
#200
0$
#210
b1000 )
b0z001000 (
b0z00111 '
b111 #
b111 %
b111 +
b111 "
b111 *
b111 ,
1$
#220
0$
#230
b1001 )
b0z001001 (
b0z00000 '
b1000 "
b1000 *
b1000 ,
b1000 #
b1000 %
b1000 +
1$
#240
0$
#250
b1010 )
b0z001010 (
b0z00001 '
b1001 #
b1001 %
b1001 +
b1001 "
b1001 *
b1001 ,
1$
#260
0$
#270
b1011 )
b0z001011 (
b0z00000 '
b1010 "
b1010 *
b1010 ,
b1010 #
b1010 %
b1010 +
1$
#280
0$
#290
b1100 )
b0z001100 (
b0z00011 '
b1011 #
b1011 %
b1011 +
b1011 "
b1011 *
b1011 ,
1$
