Contadores/probador_contador.v
//Proyecto II
//14-11-2012
//Version 1.0

//Probador

module probador_contador
                    
(output reg push0,
output reg push1,
output reg push2,
output reg push3,
output reg push4,
output reg req,
output reg [2:0] idx,
  output reg clk,
  input [5:0] data,
  input valid);

    initial clk <= 0;
    initial push0 <= 0;
    initial push1 <= 0;
    initial push2 <= 0;
    initial push3 <= 0;
    initial push4 <= 0;
    initial req <= 0;
    initial idx <=0;
    
    always #1 clk <= ~clk;

	initial begin
	$dumpfile("contador.vcd");
	$dumpvars;

    @(posedge clk);
    @(posedge clk);
    push0 = 1;
    @(posedge clk);
    req = 1;
    @(posedge clk);
    @(posedge clk);
    #0.9  push1 = 1; 
    @(posedge clk);
    @(posedge clk);
    #0.9 push2 = 1;
    @(posedge clk);
    @(posedge clk);
    #0.9 push0 = 0;

    @(posedge clk);
    @(posedge clk);
    #0.9 idx = 1;
    @(posedge clk);
    @(posedge clk);
    @(posedge clk);

	#3 $finish;
    
	end

endmodule

Contadores/contador_synth.v
/* Generated by Yosys 0.9 (git sha1 1979e0b) */

(* top =  1  *)
(* src = "contador_synth.v:6" *)
module contador_synth(push0, push1, push2, push3, push4, req, idx, clk, data, valid);
  (* src = "contador_synth.v:26" *)
  wire [3:0] _000_;
  (* src = "contador_synth.v:26" *)
  wire [3:0] _001_;
  (* src = "contador_synth.v:26" *)
  wire [3:0] _002_;
  (* src = "contador_synth.v:26" *)
  wire [3:0] _003_;
  (* src = "contador_synth.v:26" *)
  wire [3:0] _004_;
  (* src = "contador_synth.v:26" *)
  wire [5:0] _005_;
  (* src = "contador_synth.v:26" *)
  wire [5:0] _006_;
  (* src = "contador_synth.v:29" *)
  (* unused_bits = "4" *)
  wire [31:0] _007_;
  (* src = "contador_synth.v:31" *)
  (* unused_bits = "4" *)
  wire [31:0] _008_;
  (* src = "contador_synth.v:33" *)
  (* unused_bits = "4" *)
  wire [31:0] _009_;
  (* src = "contador_synth.v:35" *)
  (* unused_bits = "4" *)
  wire [31:0] _010_;
  (* src = "contador_synth.v:37" *)
  (* unused_bits = "4" *)
  wire [31:0] _011_;
  wire _012_;
  wire _013_;
  wire _014_;
  wire _015_;
  wire [1:0] _016_;
  wire _017_;
  wire [1:0] _018_;
  wire _019_;
  wire [1:0] _020_;
  wire _021_;
  wire [1:0] _022_;
  wire _023_;
  wire [1:0] _024_;
  wire _025_;
  wire _026_;
  wire [2:0] _027_;
  wire [2:0] _028_;
  wire _029_;
  wire _030_;
  wire _031_;
  wire _032_;
  (* src = "contador_synth.v:45|contador_synth.v:40|<techmap.v>:432" *)
  wire [29:0] _033_;
  (* src = "contador_synth.v:45|contador_synth.v:40|<techmap.v>:428" *)
  wire [5:0] _034_;
  wire _035_;
  wire _036_;
  wire _037_;
  wire _038_;
  wire _039_;
  (* src = "contador_synth.v:29|<techmap.v>:260|<techmap.v>:203" *)
  (* unused_bits = "3" *)
  wire [31:0] _040_;
  (* src = "contador_synth.v:31|contador_synth.v:29|<techmap.v>:260|<techmap.v>:203" *)
  (* unused_bits = "3" *)
  wire [31:0] _041_;
  (* src = "contador_synth.v:33|contador_synth.v:29|<techmap.v>:260|<techmap.v>:203" *)
  (* unused_bits = "3" *)
  wire [31:0] _042_;
  (* src = "contador_synth.v:35|contador_synth.v:29|<techmap.v>:260|<techmap.v>:203" *)
  (* unused_bits = "3" *)
  wire [31:0] _043_;
  (* src = "contador_synth.v:37|contador_synth.v:29|<techmap.v>:260|<techmap.v>:203" *)
  (* unused_bits = "3" *)
  wire [31:0] _044_;
  (* src = "contador_synth.v:45|contador_synth.v:40|<techmap.v>:445" *)
  wire _045_;
  (* src = "contador_synth.v:14" *)
  input clk;
  (* init = 4'h0 *)
  (* src = "contador_synth.v:20" *)
  reg [3:0] cuenta0 = 4'h0;
  (* init = 4'h0 *)
  (* src = "contador_synth.v:21" *)
  reg [3:0] cuenta1 = 4'h0;
  (* init = 4'h0 *)
  (* src = "contador_synth.v:22" *)
  reg [3:0] cuenta2 = 4'h0;
  (* init = 4'h0 *)
  (* src = "contador_synth.v:23" *)
  reg [3:0] cuenta3 = 4'h0;
  (* init = 4'h0 *)
  (* src = "contador_synth.v:24" *)
  reg [3:0] cuenta4 = 4'h0;
  (* init = 6'h00 *)
  (* src = "contador_synth.v:15" *)
  output [5:0] data;
  reg [5:0] data = 6'h00;
  (* src = "contador_synth.v:13" *)
  input [2:0] idx;
  (* src = "contador_synth.v:7" *)
  input push0;
  (* src = "contador_synth.v:8" *)
  input push1;
  (* src = "contador_synth.v:9" *)
  input push2;
  (* src = "contador_synth.v:10" *)
  input push3;
  (* src = "contador_synth.v:11" *)
  input push4;
  (* src = "contador_synth.v:12" *)
  input req;
  (* init = 1'h0 *)
  (* src = "contador_synth.v:16" *)
  output valid;
  reg valid = 1'h0;
  assign _032_ = _012_ |(* src = "contador_synth.v:45|contador_synth.v:40" *)  _028_[2];
  assign _013_ = _027_[0] |(* src = "contador_synth.v:44|contador_synth.v:40" *)  _027_[1];
  assign _029_ = _013_ |(* src = "contador_synth.v:44|contador_synth.v:40" *)  idx[2];
  assign _014_ = idx[0] |(* src = "contador_synth.v:43|contador_synth.v:40" *)  _027_[1];
  assign _030_ = _014_ |(* src = "contador_synth.v:43|contador_synth.v:40" *)  idx[2];
  assign _015_ = _027_[0] |(* src = "contador_synth.v:42|contador_synth.v:40" *)  idx[1];
  assign _031_ = _015_ |(* src = "contador_synth.v:42|contador_synth.v:40" *)  idx[2];
  assign _016_[0] = _033_[1] |(* src = "contador_synth.v:45|contador_synth.v:40|<techmap.v>:441" *)  _033_[7];
  assign _016_[1] = _033_[13] |(* src = "contador_synth.v:45|contador_synth.v:40|<techmap.v>:441" *)  _033_[19];
  assign _017_ = _016_[0] |(* src = "contador_synth.v:45|contador_synth.v:40|<techmap.v>:441" *)  _016_[1];
  assign _034_[1] = _017_ |(* src = "contador_synth.v:45|contador_synth.v:40|<techmap.v>:441" *)  _033_[25];
  assign _018_[0] = _033_[3] |(* src = "contador_synth.v:45|contador_synth.v:40|<techmap.v>:441" *)  _033_[9];
  assign _018_[1] = _033_[15] |(* src = "contador_synth.v:45|contador_synth.v:40|<techmap.v>:441" *)  _033_[21];
  assign _019_ = _018_[0] |(* src = "contador_synth.v:45|contador_synth.v:40|<techmap.v>:441" *)  _018_[1];
  assign _034_[3] = _019_ |(* src = "contador_synth.v:45|contador_synth.v:40|<techmap.v>:441" *)  _033_[27];
  assign _020_[0] = _033_[2] |(* src = "contador_synth.v:45|contador_synth.v:40|<techmap.v>:441" *)  _033_[8];
  assign _020_[1] = _033_[14] |(* src = "contador_synth.v:45|contador_synth.v:40|<techmap.v>:441" *)  _033_[20];
  assign _021_ = _020_[0] |(* src = "contador_synth.v:45|contador_synth.v:40|<techmap.v>:441" *)  _020_[1];
  assign _034_[2] = _021_ |(* src = "contador_synth.v:45|contador_synth.v:40|<techmap.v>:441" *)  _033_[26];
  assign _022_[0] = _033_[0] |(* src = "contador_synth.v:45|contador_synth.v:40|<techmap.v>:441" *)  _033_[6];
  assign _022_[1] = _033_[12] |(* src = "contador_synth.v:45|contador_synth.v:40|<techmap.v>:441" *)  _033_[18];
  assign _023_ = _022_[0] |(* src = "contador_synth.v:45|contador_synth.v:40|<techmap.v>:441" *)  _022_[1];
  assign _034_[0] = _023_ |(* src = "contador_synth.v:45|contador_synth.v:40|<techmap.v>:441" *)  _033_[24];
  assign _024_[0] = _035_ |(* src = "contador_synth.v:45|contador_synth.v:40|<techmap.v>:445" *)  _036_;
  assign _024_[1] = _037_ |(* src = "contador_synth.v:45|contador_synth.v:40|<techmap.v>:445" *)  _038_;
  assign _025_ = _024_[0] |(* src = "contador_synth.v:45|contador_synth.v:40|<techmap.v>:445" *)  _024_[1];
  assign _045_ = _025_ |(* src = "contador_synth.v:45|contador_synth.v:40|<techmap.v>:445" *)  _039_;
  assign _012_ = idx[0] |(* src = "contador_synth.v:41|contador_synth.v:40" *)  idx[1];
  assign _026_ = _012_ |(* src = "contador_synth.v:41|contador_synth.v:40" *)  idx[2];
  assign _035_ = ~(* src = "contador_synth.v:45|contador_synth.v:40" *) _032_;
  assign _036_ = ~(* src = "contador_synth.v:44|contador_synth.v:40" *) _029_;
  assign _037_ = ~(* src = "contador_synth.v:43|contador_synth.v:40" *) _030_;
  assign _038_ = ~(* src = "contador_synth.v:42|contador_synth.v:40" *) _031_;
  assign _039_ = ~(* src = "contador_synth.v:41|contador_synth.v:40" *) _026_;
  assign _003_[0] = push3 ? (* src = "contador_synth.v:35" *) _010_[0] : cuenta3[0];
  assign _003_[1] = push3 ? (* src = "contador_synth.v:35" *) _010_[1] : cuenta3[1];
  assign _003_[2] = push3 ? (* src = "contador_synth.v:35" *) _010_[2] : cuenta3[2];
  assign _003_[3] = push3 ? (* src = "contador_synth.v:35" *) _010_[3] : cuenta3[3];
  assign _005_[0] = req ? (* src = "contador_synth.v:39" *) _006_[0] : data[0];
  assign _005_[1] = req ? (* src = "contador_synth.v:39" *) _006_[1] : data[1];
  assign _005_[2] = req ? (* src = "contador_synth.v:39" *) _006_[2] : data[2];
  assign _005_[3] = req ? (* src = "contador_synth.v:39" *) _006_[3] : data[3];
  assign _005_[4] = req ? (* src = "contador_synth.v:39" *) 1'h0 : data[4];
  assign _005_[5] = req ? (* src = "contador_synth.v:39" *) 1'h0 : data[5];
  assign _004_[0] = push4 ? (* src = "contador_synth.v:37" *) _011_[0] : cuenta4[0];
  assign _004_[1] = push4 ? (* src = "contador_synth.v:37" *) _011_[1] : cuenta4[1];
  assign _004_[2] = push4 ? (* src = "contador_synth.v:37" *) _011_[2] : cuenta4[2];
  assign _004_[3] = push4 ? (* src = "contador_synth.v:37" *) _011_[3] : cuenta4[3];
  assign _000_[0] = push0 ? (* src = "contador_synth.v:29" *) _007_[0] : cuenta0[0];
  assign _000_[1] = push0 ? (* src = "contador_synth.v:29" *) _007_[1] : cuenta0[1];
  assign _000_[2] = push0 ? (* src = "contador_synth.v:29" *) _007_[2] : cuenta0[2];
  assign _000_[3] = push0 ? (* src = "contador_synth.v:29" *) _007_[3] : cuenta0[3];
  assign _002_[0] = push2 ? (* src = "contador_synth.v:33" *) _009_[0] : cuenta2[0];
  assign _002_[1] = push2 ? (* src = "contador_synth.v:33" *) _009_[1] : cuenta2[1];
  assign _002_[2] = push2 ? (* src = "contador_synth.v:33" *) _009_[2] : cuenta2[2];
  assign _002_[3] = push2 ? (* src = "contador_synth.v:33" *) _009_[3] : cuenta2[3];
  assign _001_[0] = push1 ? (* src = "contador_synth.v:31" *) _008_[0] : cuenta1[0];
  assign _001_[1] = push1 ? (* src = "contador_synth.v:31" *) _008_[1] : cuenta1[1];
  assign _001_[2] = push1 ? (* src = "contador_synth.v:31" *) _008_[2] : cuenta1[2];
  assign _001_[3] = push1 ? (* src = "contador_synth.v:31" *) _008_[3] : cuenta1[3];
  assign _006_[0] = _045_ ? (* src = "contador_synth.v:45|contador_synth.v:40|<techmap.v>:445" *) _034_[0] : 1'h0;
  assign _006_[1] = _045_ ? (* src = "contador_synth.v:45|contador_synth.v:40|<techmap.v>:445" *) _034_[1] : 1'h0;
  assign _006_[2] = _045_ ? (* src = "contador_synth.v:45|contador_synth.v:40|<techmap.v>:445" *) _034_[2] : 1'h0;
  assign _006_[3] = _045_ ? (* src = "contador_synth.v:45|contador_synth.v:40|<techmap.v>:445" *) _034_[3] : 1'h0;
  (* src = "contador_synth.v:26" *)
  always @(posedge clk)
      data[0] <= _005_[0];
  (* src = "contador_synth.v:26" *)
  always @(posedge clk)
      data[1] <= _005_[1];
  (* src = "contador_synth.v:26" *)
  always @(posedge clk)
      data[2] <= _005_[2];
  (* src = "contador_synth.v:26" *)
  always @(posedge clk)
      data[3] <= _005_[3];
  (* src = "contador_synth.v:26" *)
  always @(posedge clk)
      data[4] <= _005_[4];
  (* src = "contador_synth.v:26" *)
  always @(posedge clk)
      data[5] <= _005_[5];
  (* src = "contador_synth.v:26" *)
  always @(posedge clk)
      valid <= req;
  (* src = "contador_synth.v:26" *)
  always @(posedge clk)
      cuenta0[0] <= _000_[0];
  (* src = "contador_synth.v:26" *)
  always @(posedge clk)
      cuenta0[1] <= _000_[1];
  (* src = "contador_synth.v:26" *)
  always @(posedge clk)
      cuenta0[2] <= _000_[2];
  (* src = "contador_synth.v:26" *)
  always @(posedge clk)
      cuenta0[3] <= _000_[3];
  (* src = "contador_synth.v:26" *)
  always @(posedge clk)
      cuenta1[0] <= _001_[0];
  (* src = "contador_synth.v:26" *)
  always @(posedge clk)
      cuenta1[1] <= _001_[1];
  (* src = "contador_synth.v:26" *)
  always @(posedge clk)
      cuenta1[2] <= _001_[2];
  (* src = "contador_synth.v:26" *)
  always @(posedge clk)
      cuenta1[3] <= _001_[3];
  (* src = "contador_synth.v:26" *)
  always @(posedge clk)
      cuenta2[0] <= _002_[0];
  (* src = "contador_synth.v:26" *)
  always @(posedge clk)
      cuenta2[1] <= _002_[1];
  (* src = "contador_synth.v:26" *)
  always @(posedge clk)
      cuenta2[2] <= _002_[2];
  (* src = "contador_synth.v:26" *)
  always @(posedge clk)
      cuenta2[3] <= _002_[3];
  (* src = "contador_synth.v:26" *)
  always @(posedge clk)
      cuenta3[0] <= _003_[0];
  (* src = "contador_synth.v:26" *)
  always @(posedge clk)
      cuenta3[1] <= _003_[1];
  (* src = "contador_synth.v:26" *)
  always @(posedge clk)
      cuenta3[2] <= _003_[2];
  (* src = "contador_synth.v:26" *)
  always @(posedge clk)
      cuenta3[3] <= _003_[3];
  (* src = "contador_synth.v:26" *)
  always @(posedge clk)
      cuenta4[0] <= _004_[0];
  (* src = "contador_synth.v:26" *)
  always @(posedge clk)
      cuenta4[1] <= _004_[1];
  (* src = "contador_synth.v:26" *)
  always @(posedge clk)
      cuenta4[2] <= _004_[2];
  (* src = "contador_synth.v:26" *)
  always @(posedge clk)
      cuenta4[3] <= _004_[3];
  assign _010_[1] = cuenta3[1] ^(* src = "contador_synth.v:35|contador_synth.v:29|<techmap.v>:263" *)  cuenta3[0];
  assign _010_[2] = cuenta3[2] ^(* src = "contador_synth.v:35|contador_synth.v:29|<techmap.v>:263" *)  _043_[1];
  assign _010_[3] = cuenta3[3] ^(* src = "contador_synth.v:35|contador_synth.v:29|<techmap.v>:263" *)  _043_[2];
  assign _010_[0] = cuenta3[0] ^(* src = "contador_synth.v:35|contador_synth.v:29|<techmap.v>:262" *)  1'h1;
  assign _011_[1] = cuenta4[1] ^(* src = "contador_synth.v:37|contador_synth.v:29|<techmap.v>:263" *)  cuenta4[0];
  assign _011_[2] = cuenta4[2] ^(* src = "contador_synth.v:37|contador_synth.v:29|<techmap.v>:263" *)  _044_[1];
  assign _011_[3] = cuenta4[3] ^(* src = "contador_synth.v:37|contador_synth.v:29|<techmap.v>:263" *)  _044_[2];
  assign _011_[0] = cuenta4[0] ^(* src = "contador_synth.v:37|contador_synth.v:29|<techmap.v>:262" *)  1'h1;
  assign _040_[1] = cuenta0[1] &(* src = "contador_synth.v:29|<techmap.v>:260|<techmap.v>:221" *)  cuenta0[0];
  assign _027_[1] = idx[1] ^(* src = "contador_synth.v:43|contador_synth.v:40" *)  1'h1;
  assign _040_[2] = cuenta0[2] &(* src = "contador_synth.v:29|<techmap.v>:260|<techmap.v>:229" *)  _040_[1];
  assign _027_[0] = idx[0] ^(* src = "contador_synth.v:42|contador_synth.v:40" *)  1'h1;
  assign _041_[1] = cuenta1[1] &(* src = "contador_synth.v:31|contador_synth.v:29|<techmap.v>:260|<techmap.v>:221" *)  cuenta1[0];
  assign _041_[2] = cuenta1[2] &(* src = "contador_synth.v:31|contador_synth.v:29|<techmap.v>:260|<techmap.v>:229" *)  _041_[1];
  assign _042_[1] = cuenta2[1] &(* src = "contador_synth.v:33|contador_synth.v:29|<techmap.v>:260|<techmap.v>:221" *)  cuenta2[0];
  assign _042_[2] = cuenta2[2] &(* src = "contador_synth.v:33|contador_synth.v:29|<techmap.v>:260|<techmap.v>:229" *)  _042_[1];
  assign _043_[1] = cuenta3[1] &(* src = "contador_synth.v:35|contador_synth.v:29|<techmap.v>:260|<techmap.v>:221" *)  cuenta3[0];
  assign _043_[2] = cuenta3[2] &(* src = "contador_synth.v:35|contador_synth.v:29|<techmap.v>:260|<techmap.v>:229" *)  _043_[1];
  assign _044_[1] = cuenta4[1] &(* src = "contador_synth.v:37|contador_synth.v:29|<techmap.v>:260|<techmap.v>:221" *)  cuenta4[0];
  assign _044_[2] = cuenta4[2] &(* src = "contador_synth.v:37|contador_synth.v:29|<techmap.v>:260|<techmap.v>:229" *)  _044_[1];
  assign _033_[24] = cuenta0[0] &(* src = "contador_synth.v:45|contador_synth.v:40|<techmap.v>:434" *)  _039_;
  assign _033_[25] = cuenta0[1] &(* src = "contador_synth.v:45|contador_synth.v:40|<techmap.v>:434" *)  _039_;
  assign _033_[26] = cuenta0[2] &(* src = "contador_synth.v:45|contador_synth.v:40|<techmap.v>:434" *)  _039_;
  assign _033_[27] = cuenta0[3] &(* src = "contador_synth.v:45|contador_synth.v:40|<techmap.v>:434" *)  _039_;
  assign _033_[18] = cuenta1[0] &(* src = "contador_synth.v:45|contador_synth.v:40|<techmap.v>:434" *)  _038_;
  assign _033_[19] = cuenta1[1] &(* src = "contador_synth.v:45|contador_synth.v:40|<techmap.v>:434" *)  _038_;
  assign _033_[20] = cuenta1[2] &(* src = "contador_synth.v:45|contador_synth.v:40|<techmap.v>:434" *)  _038_;
  assign _033_[21] = cuenta1[3] &(* src = "contador_synth.v:45|contador_synth.v:40|<techmap.v>:434" *)  _038_;
  assign _033_[12] = cuenta2[0] &(* src = "contador_synth.v:45|contador_synth.v:40|<techmap.v>:434" *)  _037_;
  assign _033_[13] = cuenta2[1] &(* src = "contador_synth.v:45|contador_synth.v:40|<techmap.v>:434" *)  _037_;
  assign _033_[14] = cuenta2[2] &(* src = "contador_synth.v:45|contador_synth.v:40|<techmap.v>:434" *)  _037_;
  assign _033_[15] = cuenta2[3] &(* src = "contador_synth.v:45|contador_synth.v:40|<techmap.v>:434" *)  _037_;
  assign _033_[6] = cuenta3[0] &(* src = "contador_synth.v:45|contador_synth.v:40|<techmap.v>:434" *)  _036_;
  assign _033_[7] = cuenta3[1] &(* src = "contador_synth.v:45|contador_synth.v:40|<techmap.v>:434" *)  _036_;
  assign _033_[8] = cuenta3[2] &(* src = "contador_synth.v:45|contador_synth.v:40|<techmap.v>:434" *)  _036_;
  assign _033_[9] = cuenta3[3] &(* src = "contador_synth.v:45|contador_synth.v:40|<techmap.v>:434" *)  _036_;
  assign _033_[0] = cuenta4[0] &(* src = "contador_synth.v:45|contador_synth.v:40|<techmap.v>:434" *)  _035_;
  assign _033_[1] = cuenta4[1] &(* src = "contador_synth.v:45|contador_synth.v:40|<techmap.v>:434" *)  _035_;
  assign _033_[2] = cuenta4[2] &(* src = "contador_synth.v:45|contador_synth.v:40|<techmap.v>:434" *)  _035_;
  assign _033_[3] = cuenta4[3] &(* src = "contador_synth.v:45|contador_synth.v:40|<techmap.v>:434" *)  _035_;
  assign _007_[1] = cuenta0[1] ^(* src = "contador_synth.v:29|<techmap.v>:263" *)  cuenta0[0];
  assign _007_[2] = cuenta0[2] ^(* src = "contador_synth.v:29|<techmap.v>:263" *)  _040_[1];
  assign _007_[3] = cuenta0[3] ^(* src = "contador_synth.v:29|<techmap.v>:263" *)  _040_[2];
  assign _007_[0] = cuenta0[0] ^(* src = "contador_synth.v:29|<techmap.v>:262" *)  1'h1;
  assign _008_[1] = cuenta1[1] ^(* src = "contador_synth.v:31|contador_synth.v:29|<techmap.v>:263" *)  cuenta1[0];
  assign _008_[2] = cuenta1[2] ^(* src = "contador_synth.v:31|contador_synth.v:29|<techmap.v>:263" *)  _041_[1];
  assign _008_[3] = cuenta1[3] ^(* src = "contador_synth.v:31|contador_synth.v:29|<techmap.v>:263" *)  _041_[2];
  assign _008_[0] = cuenta1[0] ^(* src = "contador_synth.v:31|contador_synth.v:29|<techmap.v>:262" *)  1'h1;
  assign _009_[1] = cuenta2[1] ^(* src = "contador_synth.v:33|contador_synth.v:29|<techmap.v>:263" *)  cuenta2[0];
  assign _009_[2] = cuenta2[2] ^(* src = "contador_synth.v:33|contador_synth.v:29|<techmap.v>:263" *)  _042_[1];
  assign _009_[3] = cuenta2[3] ^(* src = "contador_synth.v:33|contador_synth.v:29|<techmap.v>:263" *)  _042_[2];
  assign _009_[0] = cuenta2[0] ^(* src = "contador_synth.v:33|contador_synth.v:29|<techmap.v>:262" *)  1'h1;
  assign _028_[2] = idx[2] ^(* src = "contador_synth.v:45|contador_synth.v:40" *)  1'h1;
  assign _006_[5:4] = 2'h0;
  assign _007_[31:5] = 27'h0000000;
  assign _008_[31:5] = 27'h0000000;
  assign _009_[31:5] = 27'h0000000;
  assign _010_[31:5] = 27'h0000000;
  assign _011_[31:5] = 27'h0000000;
  assign _027_[2] = idx[2];
  assign _028_[1:0] = idx[1:0];
  assign { _033_[29:28], _033_[23:22], _033_[17:16], _033_[11:10], _033_[5:4] } = 10'h000;
  assign _034_[5:4] = 2'h0;
  assign { _040_[31:3], _040_[0] } = { 28'h0000000, _007_[4], cuenta0[0] };
  assign { _041_[31:3], _041_[0] } = { 28'h0000000, _008_[4], cuenta1[0] };
  assign { _042_[31:3], _042_[0] } = { 28'h0000000, _009_[4], cuenta2[0] };
  assign { _043_[31:3], _043_[0] } = { 28'h0000000, _010_[4], cuenta3[0] };
  assign { _044_[31:3], _044_[0] } = { 28'h0000000, _011_[4], cuenta4[0] };
endmodule

Contadores/contador.v
//Proyecto II
//13-11-2021
//Version 1
//Modulo de Contadores

module contador 
(input push0,
input push1,
input push2,
input push3,
input push4,
input req,
input [2:0] idx,
  input clk,
  output reg [5:0] data,
  output reg valid);

initial data <= 0;
initial valid <= 0;
reg [3:0] cuenta0 = 0;
reg [3:0] cuenta1 = 0;
reg [3:0] cuenta2 = 0;
reg [3:0] cuenta3 = 0;
reg [3:0] cuenta4 = 0;

always @(posedge clk) begin
  //Por cada push se incrementa la cantidad de datos
  
  if (push0) cuenta0 <= cuenta0 + 1;

  if (push1) cuenta1 <= cuenta1 + 1;

  if (push2) cuenta2 <= cuenta2 + 1;

  if (push3) cuenta3 <= cuenta3 + 1;

  if (push4) cuenta4 <= cuenta4 + 1;

  if (req) begin
    case (idx)
      0:  data <= cuenta0;
      1:  data <= cuenta1;
      2:  data <= cuenta2;
      3:  data <= cuenta3;
      4:  data <= cuenta4;

      default: data = 0;
    endcase
    valid <= 1;
  end
  else valid <= 0;
end

endmodule

Contadores/banco_contador.v
//Proyecto II
//14-11-2012
//Version 1.0

//Banco de pruebas para contador

// escala	unidad temporal (valor de "#1") / precisión
`timescale 	1ns	/ 100ps

// Se incluyen los archivos necesario
`include "contador.v"
`include "contador_synth.v"
`include "probador_contador.v"

module banco_contador;

    //Wires
    wire clk; //señal de reloj
	wire valid; //señal de valid
	wire valid_synth; //señal de valid
	wire req; //señal de request
	wire push0; //señal de push de FIFO 0
	wire push1; //señal de push de FIFO 1
	wire push2; //señal de push de FIFO 2
	wire push3; //señal de push de FIFO 3
	wire push4; //señal de push de FIFO 4
	wire [2:0] idx; //señal para indexar el contador
	wire [5:0]  data; //señal de cuenta
    wire [5:0]  data_synth; //señal de cuenta
    
	// Se instancia el módulo de memoria conductual
	contador conductual(/*AUTOINST*/
			    // Outputs
			    .data		(data[5:0]),
			    .valid		(valid),
			    // Inputs
			    .push0		(push0),
			    .push1		(push1),
			    .push2		(push2),
			    .push3		(push3),
			    .push4		(push4),
			    .req		(req),
			    .idx		(idx[2:0]),
			    .clk		(clk));

    contador_synth estructural(/*AUTOINST*/
			       // Outputs
			       .data		(data_synth[5:0]),
			       .valid		(valid_synth),
			       // Inputs
			       .clk		(clk),
			       .idx		(idx[2:0]),
			       .push0		(push0),
			       .push1		(push1),
			       .push2		(push2),
			       .push3		(push3),
			       .push4		(push4),
			       .req		(req));

	// Probador
	probador_contador probador(/*AUTOINST*/
				   // Outputs
				   .push0		(push0),
				   .push1		(push1),
				   .push2		(push2),
				   .push3		(push3),
				   .push4		(push4),
				   .req			(req),
				   .idx			(idx[2:0]),
				   .clk			(clk),
				   // Inputs
				   .data		(data[5:0]),
				   .valid		(valid));

endmodule

Contadores/contador.vcd
$date
	Thu Nov 18 21:38:34 2021
$end
$version
	Icarus Verilog
$end
$timescale
	100ps
$end
$scope module banco_contador $end
$var wire 1 ! valid_synth $end
$var wire 1 " valid $end
$var wire 1 # req $end
$var wire 1 $ push4 $end
$var wire 1 % push3 $end
$var wire 1 & push2 $end
$var wire 1 ' push1 $end
$var wire 1 ( push0 $end
$var wire 3 ) idx [2:0] $end
$var wire 6 * data_synth [5:0] $end
$var wire 6 + data [5:0] $end
$var wire 1 , clk $end
$scope module conductual $end
$var wire 1 # req $end
$var wire 1 $ push4 $end
$var wire 1 % push3 $end
$var wire 1 & push2 $end
$var wire 1 ' push1 $end
$var wire 1 ( push0 $end
$var wire 3 - idx [2:0] $end
$var wire 1 , clk $end
$var reg 4 . cuenta0 [3:0] $end
$var reg 4 / cuenta1 [3:0] $end
$var reg 4 0 cuenta2 [3:0] $end
$var reg 4 1 cuenta3 [3:0] $end
$var reg 4 2 cuenta4 [3:0] $end
$var reg 6 3 data [5:0] $end
$var reg 1 " valid $end
$upscope $end
$scope module estructural $end
$var wire 1 4 _012_ $end
$var wire 1 5 _013_ $end
$var wire 1 6 _014_ $end
$var wire 1 7 _015_ $end
$var wire 1 8 _017_ $end
$var wire 1 9 _019_ $end
$var wire 1 : _021_ $end
$var wire 1 ; _023_ $end
$var wire 1 < _025_ $end
$var wire 1 = _026_ $end
$var wire 1 > _029_ $end
$var wire 1 ? _030_ $end
$var wire 1 @ _031_ $end
$var wire 1 A _032_ $end
$var wire 1 B _035_ $end
$var wire 1 C _036_ $end
$var wire 1 D _037_ $end
$var wire 1 E _038_ $end
$var wire 1 F _039_ $end
$var wire 1 G _045_ $end
$var wire 1 # req $end
$var wire 1 $ push4 $end
$var wire 1 % push3 $end
$var wire 1 & push2 $end
$var wire 1 ' push1 $end
$var wire 1 ( push0 $end
$var wire 3 H idx [2:0] $end
$var wire 1 , clk $end
$var wire 32 I _044_ [31:0] $end
$var wire 32 J _043_ [31:0] $end
$var wire 32 K _042_ [31:0] $end
$var wire 32 L _041_ [31:0] $end
$var wire 32 M _040_ [31:0] $end
$var wire 6 N _034_ [5:0] $end
$var wire 30 O _033_ [29:0] $end
$var wire 3 P _028_ [2:0] $end
$var wire 3 Q _027_ [2:0] $end
$var wire 2 R _024_ [1:0] $end
$var wire 2 S _022_ [1:0] $end
$var wire 2 T _020_ [1:0] $end
$var wire 2 U _018_ [1:0] $end
$var wire 2 V _016_ [1:0] $end
$var wire 32 W _011_ [31:0] $end
$var wire 32 X _010_ [31:0] $end
$var wire 32 Y _009_ [31:0] $end
$var wire 32 Z _008_ [31:0] $end
$var wire 32 [ _007_ [31:0] $end
$var wire 6 \ _006_ [5:0] $end
$var wire 6 ] _005_ [5:0] $end
$var wire 4 ^ _004_ [3:0] $end
$var wire 4 _ _003_ [3:0] $end
$var wire 4 ` _002_ [3:0] $end
$var wire 4 a _001_ [3:0] $end
$var wire 4 b _000_ [3:0] $end
$var reg 4 c cuenta0 [3:0] $end
$var reg 4 d cuenta1 [3:0] $end
$var reg 4 e cuenta2 [3:0] $end
$var reg 4 f cuenta3 [3:0] $end
$var reg 4 g cuenta4 [3:0] $end
$var reg 6 h data [5:0] $end
$var reg 1 ! valid $end
$upscope $end
$scope module probador $end
$var wire 6 i data [5:0] $end
$var wire 1 " valid $end
$var reg 1 , clk $end
$var reg 3 j idx [2:0] $end
$var reg 1 ( push0 $end
$var reg 1 ' push1 $end
$var reg 1 & push2 $end
$var reg 1 % push3 $end
$var reg 1 $ push4 $end
$var reg 1 # req $end
$upscope $end
$upscope $end
$enddefinitions $end
#0
$dumpvars
b0 j
b0 i
b0 h
b0 g
b0 f
b0 e
b0 d
b0 c
b0 b
b0 a
b0 `
b0 _
b0 ^
b0 ]
b0 \
b0z0001 [
b0z0001 Z
b0z0001 Y
b0z0001 X
b0z0001 W
b0 V
b0 U
b0 T
b0 S
b0 R
b11 Q
b100 P
b0 O
b0 N
b0z000 M
b0z000 L
b0z000 K
b0z000 J
b0z000 I
b0 H
1G
1F
0E
0D
0C
0B
1A
1@
1?
1>
0=
0<
0;
0:
09
08
17
16
15
04
b0 3
b0 2
b0 1
b0 0
b0 /
b0 .
b0 -
0,
b0 +
b0 *
b0 )
0(
0'
0&
0%
0$
0#
0"
0!
$end
#10
1,
#20
0,
#30
b1 b
1(
1,
#40
0,
#50
b1 ]
b1 \
b1 N
b10 b
b1000000000000000000000000 O
b0z0010 [
b0z001 M
1"
b1 .
1!
b1 c
1#
1,
#60
0,
#70
b10 ]
b10 \
b10 N
b11 b
b10000000000000000000000000 O
b0z0011 [
b0z000 M
b10 c
b1 *
b1 h
b1 +
b1 3
b1 i
b10 .
1,
#80
0,
#90
b11 ]
b11 \
b11 N
b100 b
b11000000000000000000000000 O
b0z0100 [
b0z011 M
b10 +
b10 3
b10 i
b11 .
b10 *
b10 h
b11 c
1,
#99
b1 a
1'
#100
0,
#110
b100 ]
b100 \
b10 a
b100 N
b101 b
b0z0010 Z
b0z001 L
b100000000000000000000000000 O
b0z0101 [
b0z000 M
b1 d
b100 c
b11 *
b11 h
b11 +
b11 3
b11 i
b1 /
b100 .
1,
#120
0,
#130
b101 ]
b101 \
b101 N
b110 b
b11 a
b101000000000000000000000000 O
b0z0110 [
b0z001 M
b0z0011 Z
b0z000 L
b100 +
b100 3
b100 i
b10 /
b101 .
b100 *
b100 h
b101 c
b10 d
1,
#139
b1 `
1&
#140
0,
