Arbitros/Arbitro_2/probador_arbitro_2.v
//Proyecto II
//14-11-2012
//Version 1.0

//Probador 

module probador_arbitro_2
                    
(input Pop,
  output reg clk,
  input [3:0] Push,
  output reg FIFO_empty,
  output reg [3:0] Almost_full,
  output reg [1:0] class);

    initial clk <= 0;
    initial FIFO_empty <= 0;
    initial Almost_full <= 0;
    initial class <= 0;
    
    always #1 clk <= ~clk;

	initial begin
	$dumpfile("arbitro_2.vcd");
	$dumpvars;

    @(posedge clk);
    @(posedge clk);
    class = 1;
    @(posedge clk);
    @(posedge clk);
    class = 3;
    @(posedge clk);
    @(posedge clk);
    Almost_full = 4'b0100;
    @(posedge clk);
    @(posedge clk);
    Almost_full = 0;
    @(posedge clk);
    @(posedge clk);
    class = 2;
    @(posedge clk);
    @(posedge clk);
    FIFO_empty = 1;
    @(posedge clk);
    @(posedge clk);

	#3 $finish;
    
	end

endmodule

Arbitros/Arbitro_2/arbitro_2_synth.v
/* Generated by Yosys 0.9 (git sha1 1979e0b) */

(* top =  1  *)
(* src = "arbitro_2_synth.v:6" *)
module arbitro_2_synth(Pop, clk, Push, FIFO_empty, Almost_full, \class );
  (* src = "arbitro_2_synth.v:16" *)
  wire _00_;
  (* src = "arbitro_2_synth.v:16" *)
  wire [3:0] _01_;
  wire [1:0] _02_;
  wire [1:0] _03_;
  wire [1:0] _04_;
  wire [1:0] _05_;
  wire [1:0] _06_;
  wire [1:0] _07_;
  wire _08_;
  wire [1:0] _09_;
  wire _10_;
  wire _11_;
  wire _12_;
  (* src = "arbitro_2_synth.v:17" *)
  wire _13_;
  (* src = "arbitro_2_synth.v:17" *)
  wire _14_;
  (* src = "arbitro_2_synth.v:27|arbitro_2.v:23|<techmap.v>:445" *)
  wire _15_;
  (* src = "arbitro_2_synth.v:10" *)
  input [3:0] Almost_full;
  (* src = "arbitro_2_synth.v:9" *)
  input FIFO_empty;
  (* init = 1'h0 *)
  (* src = "arbitro_2_synth.v:6" *)
  output Pop;
  reg Pop = 1'h0;
  (* init = 4'h0 *)
  (* src = "arbitro_2_synth.v:8" *)
  output [3:0] Push;
  reg [3:0] Push = 4'h0;
  (* src = "arbitro_2_synth.v:11" *)
  input [1:0] \class ;
  (* src = "arbitro_2_synth.v:7" *)
  input clk;
  assign _10_ = _09_[0] |(* src = "arbitro_2_synth.v:25|arbitro_2.v:23" *)  \class [1];
  assign _06_[0] = _03_[0] |(* src = "arbitro_2_synth.v:27|arbitro_2.v:23|<techmap.v>:445" *)  _04_[0];
  assign _06_[1] = _02_[1] |(* src = "arbitro_2_synth.v:27|arbitro_2.v:23|<techmap.v>:445" *)  _05_[1];
  assign _15_ = _06_[0] |(* src = "arbitro_2_synth.v:27|arbitro_2.v:23|<techmap.v>:445" *)  _06_[1];
  assign _07_[0] = Almost_full[3] |(* src = "arbitro_2_synth.v:17" *)  Almost_full[2];
  assign _07_[1] = Almost_full[1] |(* src = "arbitro_2_synth.v:17" *)  Almost_full[0];
  assign _14_ = _07_[0] |(* src = "arbitro_2_synth.v:17" *)  _07_[1];
  assign _11_ = _09_[0] |(* src = "arbitro_2_synth.v:27|arbitro_2.v:23" *)  _09_[1];
  assign _12_ = \class [0] |(* src = "arbitro_2_synth.v:26|arbitro_2.v:23" *)  _09_[1];
  assign _08_ = \class [0] |(* src = "arbitro_2_synth.v:24|arbitro_2.v:23" *)  \class [1];
  assign _02_[1] = ~(* src = "arbitro_2_synth.v:25|arbitro_2.v:23" *) _10_;
  assign _05_[1] = ~(* src = "arbitro_2_synth.v:24|arbitro_2.v:23" *) _08_;
  assign _03_[0] = ~(* src = "arbitro_2_synth.v:27|arbitro_2.v:23" *) _11_;
  assign _04_[0] = ~(* src = "arbitro_2_synth.v:26|arbitro_2.v:23" *) _12_;
  assign _00_ = ~(* src = "arbitro_2_synth.v:17" *) _13_;
  assign _01_[0] = _15_ ? (* src = "arbitro_2_synth.v:27|arbitro_2.v:23|<techmap.v>:445" *) _05_[1] : 1'hx;
  assign _01_[1] = _15_ ? (* src = "arbitro_2_synth.v:27|arbitro_2.v:23|<techmap.v>:445" *) _02_[1] : 1'hx;
  assign _01_[2] = _15_ ? (* src = "arbitro_2_synth.v:27|arbitro_2.v:23|<techmap.v>:445" *) _04_[0] : 1'hx;
  assign _01_[3] = _15_ ? (* src = "arbitro_2_synth.v:27|arbitro_2.v:23|<techmap.v>:445" *) _03_[0] : 1'hx;
  (* src = "arbitro_2_synth.v:16" *)
  always @(posedge clk)
      Pop <= _00_;
  (* src = "arbitro_2_synth.v:16" *)
  always @(posedge clk)
      Push[0] <= _01_[0];
  (* src = "arbitro_2_synth.v:16" *)
  always @(posedge clk)
      Push[1] <= _01_[1];
  (* src = "arbitro_2_synth.v:16" *)
  always @(posedge clk)
      Push[2] <= _01_[2];
  (* src = "arbitro_2_synth.v:16" *)
  always @(posedge clk)
      Push[3] <= _01_[3];
  assign _13_ = FIFO_empty |(* src = "arbitro_2_synth.v:17" *)  _14_;
  assign _09_[1] = \class [1] ^(* src = "arbitro_2_synth.v:26|arbitro_2.v:23" *)  1'h1;
  assign _09_[0] = \class [0] ^(* src = "arbitro_2_synth.v:25|arbitro_2.v:23" *)  1'h1;
  assign _02_[0] = 1'h0;
  assign _03_[1] = 1'h0;
  assign _04_[1] = 1'h0;
  assign _05_[0] = 1'h0;
endmodule

Arbitros/Arbitro_2/arbitro_2.v
//Proyecto II
//14-11-2021
//Version 1
//Modulo de Arbitro 2

module arbitro_2 #(
  parameter DATA_WIDTH=8,          //width of data bus
  parameter ADDR_WIDTH=8)           //width of addresses buses
(output Pop,
  input clk,
  output [3:0] Push,
  input FIFO_empty,
  input [3:0] Almost_full,
  input [1:0] class);

initial Push = 0;
initial Pop = 0;

always @(posedge clk) begin
    if (FIFO_empty | |Almost_full) Pop = 0;
    else Pop = 1;

    // No tiene prioridades
    // Dependiendo del valor de class se habilitan los Pushes

    case (class)
        0: Push = 4'b0001;
        1: Push = 4'b0010;
        2: Push = 4'b0100;
        3: Push = 4'b1000;
        default: Push = 0;
    endcase

endmodule

Arbitros/Arbitro_2/banco_arbitro_2.v
//Proyecto II
//14-11-2012
//Version 1.0

//Banco de pruebas para arbitro_2

// escala	unidad temporal (valor de "#1") / precisión
`timescale 	1ns	/ 100ps

// Se incluyen los archivos necesario
`include "arbitro_2.v"
`include "arbitro_2_synth.v"
`include "probador_arbitro_2.v"

module banco_arbitro_2;

    //Wires
    wire clk; //señal de reloj
    wire Pop;
    wire Pop_synth;
    wire [3:0] Push;
    wire [3:0] Push_synth;
    wire FIFO_empty;
    wire [3:0] Almost_full;
    wire [1:0] class;
	
	// Se instancia el módulo de memoria conductual
	arbitro_2 conductual(/*AUTOINST*/
			     // Outputs
			     .Pop		(Pop),
			     .Push		(Push[3:0]),
			     // Inputs
                 .class 	(class [1:0]),
			     .clk		(clk),
			     .FIFO_empty	(FIFO_empty),
			     .Almost_full	(Almost_full[3:0]));

    arbitro_2_synth estructural(/*AUTOINST*/
				// Outputs
				.Pop		(Pop_synth),
				.Push		(Push_synth[3:0]),
				// Inputs
				.Almost_full	(Almost_full[3:0]),
				.FIFO_empty	(FIFO_empty),
				.class 	(class [1:0]),
				.clk		(clk));

	// Probador
	probador_arbitro_2 probador(/*AUTOINST*/
				    // Outputs
				    .clk		(clk),
				    .FIFO_empty		(FIFO_empty),
				    .Almost_full	(Almost_full[3:0]),
                    .class 	(class [1:0]),
				    // Inputs
				    .Pop		(Pop),
				    .Push		(Push[3:0]));

endmodule

Arbitros/Arbitro_2/arbitro_2.vcd
$date
	Mon Nov 15 22:21:25 2021
$end
$version
	Icarus Verilog
$end
$timescale
	100ps
$end
$scope module banco_arbitro_2 $end
$var wire 1 ! clk $end
$var wire 2 " class [1:0] $end
$var wire 4 # Push_synth [3:0] $end
$var wire 4 $ Push [3:0] $end
$var wire 1 % Pop_synth $end
$var wire 1 & Pop $end
$var wire 1 ' FIFO_empty $end
$var wire 4 ( Almost_full [3:0] $end
$scope module conductual $end
$var wire 1 ! clk $end
$var wire 2 ) class [1:0] $end
$var wire 1 ' FIFO_empty $end
$var wire 4 * Almost_full [3:0] $end
$var reg 1 & Pop $end
$var reg 4 + Push [3:0] $end
$upscope $end
$scope module estructural $end
$var wire 1 , _00_ $end
$var wire 1 - _08_ $end
$var wire 1 . _10_ $end
$var wire 1 / _11_ $end
$var wire 1 0 _12_ $end
$var wire 1 1 _13_ $end
$var wire 1 2 _14_ $end
$var wire 1 3 _15_ $end
$var wire 1 ! clk $end
$var wire 2 4 class [1:0] $end
$var wire 2 5 _09_ [1:0] $end
$var wire 2 6 _07_ [1:0] $end
$var wire 2 7 _06_ [1:0] $end
$var wire 2 8 _05_ [1:0] $end
$var wire 2 9 _04_ [1:0] $end
$var wire 2 : _03_ [1:0] $end
$var wire 2 ; _02_ [1:0] $end
$var wire 4 < _01_ [3:0] $end
$var wire 1 ' FIFO_empty $end
$var wire 4 = Almost_full [3:0] $end
$var reg 1 % Pop $end
$var reg 4 > Push [3:0] $end
$upscope $end
$scope module probador $end
$var wire 1 & Pop $end
$var wire 4 ? Push [3:0] $end
$var reg 4 @ Almost_full [3:0] $end
$var reg 1 ' FIFO_empty $end
$var reg 2 A class [1:0] $end
$var reg 1 ! clk $end
$upscope $end
$upscope $end
$enddefinitions $end
#0
$dumpvars
b0 A
b0 @
b0 ?
b0 >
b0 =
b1 <
b0 ;
b0 :
b0 9
b10 8
b10 7
b0 6
b11 5
b0 4
13
02
01
10
1/
1.
0-
1,
b0 +
b0 *
b0 )
b0 (
0'
0&
0%
b0 $
b0 #
b0 "
0!
$end
#10
1%
b1 #
b1 >
b1 $
b1 +
b1 ?
1&
1!
#20
0!
#30
13
b10 ;
b10 <
b10 7
0.
b0 8
b10 5
1-
b1 "
b1 )
b1 4
b1 A
1!
#40
0!
#50
b10 #
b10 >
b10 $
b10 +
b10 ?
1!
#60
0!
#70
13
b1 :
b1000 <
b1 7
0/
b0 ;
b0 5
1.
b11 "
b11 )
b11 4
b11 A
1!
#80
0!
#90
b1000 #
b1000 >
b1000 $
b1000 +
b1000 ?
1!
#100
0!
#110
0,
11
12
b1 6
b100 (
b100 *
b100 =
b100 @
1!
#120
0!
#130
0%
0&
1!
#140
0!
#150
1,
01
02
b0 6
b0 (
b0 *
b0 =
b0 @
1!
#160
0!
#170
1%
1&
1!
#180
0!
#190
b0 :
b100 <
1/
b1 9
b1 5
00
b10 "
b10 )
b10 4
b10 A
1!
#200
0!
#210
b100 #
b100 >
b100 $
b100 +
b100 ?
1!
#220
0!
#230
0,
11
1'
1!
#240
0!
#250
0%
0&
1!
