FSM/probador_FSM.v
//Proyecto II
//Desarrollo de FSM
//20-11-2012
//Version 1.0

//Probador

module probador_FSM (output reg reset,
            output reg clk,
            output reg init,
            output reg [2:0] umbral_alto,
            output reg [2:0] umbral_bajo,
            output reg [9:0] FIFO_empty,
            input idle,
            input [2:0] interno_alto,
            input [2:0] interno_bajo);

    initial begin
        reset <= 0;
        init <= 0;
        umbral_alto <= 5;
        clk <= 0;
        umbral_bajo <= 1;
        FIFO_empty <= 10'b1111111111;
    end
    always #1 clk <= ~clk;

	initial begin
	$dumpfile("FSM.vcd");
	$dumpvars;

    @(posedge clk);
    @(posedge clk);
    reset <= 1;
    umbral_bajo <= 3;
    umbral_alto <= 6;
    @(posedge clk);
    @(posedge clk);
    @(posedge clk);
    @(posedge clk);
    FIFO_empty <= 1;
    @(posedge clk);
    umbral_bajo <= 2;
    umbral_alto <= 7;
    @(posedge clk);
    @(posedge clk);
    @(posedge clk);
    init = 1;
    @(posedge clk);
    init = 0;
    @(posedge clk);
    @(posedge clk);

	#3 $finish;
    
	end

endmodule

FSM/FSM_synth.v
/* Generated by Yosys 0.9 (git sha1 1979e0b) */

(* top =  1  *)
(* src = "FSM_synth.v:5" *)
module FSM_synth(reset, clk, init, umbral_alto, umbral_bajo, FIFO_empty, idle, interno_alto, interno_bajo);
  (* src = "FSM_synth.v:24" *)
  wire [2:0] _000_;
  (* src = "FSM_synth.v:24" *)
  wire [2:0] _001_;
  (* src = "FSM_synth.v:41" *)
  wire _002_;
  wire _003_;
  wire _004_;
  wire _005_;
  wire _006_;
  wire _007_;
  wire _008_;
  wire _009_;
  wire _010_;
  wire [3:0] _011_;
  wire _012_;
  wire _013_;
  wire _014_;
  wire _015_;
  wire _016_;
  wire _017_;
  wire _018_;
  wire [4:0] _019_;
  wire [1:0] _020_;
  wire _021_;
  wire _022_;
  wire _023_;
  wire _024_;
  wire [1:0] _025_;
  wire [9:0] _026_;
  wire [2:0] _027_;
  wire _028_;
  wire _029_;
  wire _030_;
  wire _031_;
  wire _032_;
  wire _033_;
  wire _034_;
  (* src = "FSM_synth.v:10" *)
  input [9:0] FIFO_empty;
  (* src = "FSM_synth.v:6" *)
  input clk;
  (* onehot = 32'd1 *)
  reg [3:0] estado;
  (* src = "FSM_synth.v:11" *)
  output idle;
  (* src = "FSM_synth.v:7" *)
  input init;
  (* src = "FSM_synth.v:12" *)
  output [2:0] interno_alto;
  (* src = "FSM_synth.v:21" *)
  reg [2:0] interno_alto_d;
  (* src = "FSM_synth.v:13" *)
  output [2:0] interno_bajo;
  (* src = "FSM_synth.v:22" *)
  reg [2:0] interno_bajo_d;
  (* src = "FSM_synth.v:5" *)
  input reset;
  (* src = "FSM_synth.v:8" *)
  input [2:0] umbral_alto;
  (* src = "FSM_synth.v:9" *)
  input [2:0] umbral_bajo;
  assign _028_ = _025_[0] | _025_[1];
  assign _011_[3] = _003_ | _004_;
  assign _029_ = _025_[0] | _002_;
  assign _018_ = _025_[0] | init;
  assign _030_ = _018_ | _002_;
  assign _019_[0] = _026_[0] |(* src = "FSM_synth.v:81" *)  _026_[1];
  assign _019_[1] = _026_[2] |(* src = "FSM_synth.v:81" *)  _026_[3];
  assign _019_[2] = _026_[4] |(* src = "FSM_synth.v:81" *)  _026_[5];
  assign _019_[3] = _026_[6] |(* src = "FSM_synth.v:81" *)  _026_[7];
  assign _019_[4] = _026_[8] |(* src = "FSM_synth.v:81" *)  _026_[9];
  assign _020_[0] = _019_[0] |(* src = "FSM_synth.v:81" *)  _019_[1];
  assign _020_[1] = _019_[2] |(* src = "FSM_synth.v:81" *)  _019_[3];
  assign _021_ = _020_[0] |(* src = "FSM_synth.v:81" *)  _020_[1];
  assign _031_ = _021_ |(* src = "FSM_synth.v:81" *)  _019_[4];
  assign _022_ = _009_ | _010_;
  assign _011_[2] = _022_ | _008_;
  assign _032_ = _023_ | _025_[1];
  assign _023_ = _025_[0] | _027_[1];
  assign _033_ = _023_ | _002_;
  assign _024_ = _006_ | _007_;
  assign _011_[1] = _024_ | _005_;
  assign _034_ = _018_ | _025_[1];
  assign _014_ = ~_028_;
  assign _012_ = ~_029_;
  assign _017_ = ~_030_;
  assign _002_ = ~(* src = "FSM_synth.v:81" *) _031_;
  assign _016_ = ~_032_;
  assign _015_ = ~_033_;
  assign _013_ = ~_034_;
  assign idle = estado[1] ? (* src = "FSM_synth.v:66|FSM.v:52" *) _002_ : 1'h0;
  assign interno_bajo[0] = estado[2] ? (* src = "FSM_synth.v:58|FSM.v:52" *) umbral_bajo[0] : interno_bajo_d[0];
  assign interno_bajo[1] = estado[2] ? (* src = "FSM_synth.v:58|FSM.v:52" *) umbral_bajo[1] : interno_bajo_d[1];
  assign interno_bajo[2] = estado[2] ? (* src = "FSM_synth.v:58|FSM.v:52" *) umbral_bajo[2] : interno_bajo_d[2];
  assign interno_alto[0] = estado[2] ? (* src = "FSM_synth.v:58|FSM.v:52" *) umbral_alto[0] : interno_alto_d[0];
  assign interno_alto[1] = estado[2] ? (* src = "FSM_synth.v:58|FSM.v:52" *) umbral_alto[1] : interno_alto_d[1];
  assign interno_alto[2] = estado[2] ? (* src = "FSM_synth.v:58|FSM.v:52" *) umbral_alto[2] : interno_alto_d[2];
  assign _001_[0] = reset ? (* src = "FSM_synth.v:26" *) interno_bajo[0] : 1'h0;
  assign _001_[1] = reset ? (* src = "FSM_synth.v:26" *) interno_bajo[1] : 1'h0;
  assign _001_[2] = reset ? (* src = "FSM_synth.v:26" *) interno_bajo[2] : 1'h0;
  assign _000_[0] = reset ? (* src = "FSM_synth.v:26" *) interno_alto[0] : 1'h0;
  assign _000_[1] = reset ? (* src = "FSM_synth.v:26" *) interno_alto[1] : 1'h0;
  assign _000_[2] = reset ? (* src = "FSM_synth.v:26" *) interno_alto[2] : 1'h0;
  assign _011_[0] = ~reset;
  always @(posedge clk)
      estado[0] <= _011_[0];
  always @(posedge clk)
      estado[1] <= _011_[1];
  always @(posedge clk)
      estado[2] <= _011_[2];
  always @(posedge clk)
      estado[3] <= _011_[3];
  (* src = "FSM_synth.v:24" *)
  always @(posedge clk)
      interno_alto_d[0] <= _000_[0];
  (* src = "FSM_synth.v:24" *)
  always @(posedge clk)
      interno_alto_d[1] <= _000_[1];
  (* src = "FSM_synth.v:24" *)
  always @(posedge clk)
      interno_alto_d[2] <= _000_[2];
  (* src = "FSM_synth.v:24" *)
  always @(posedge clk)
      interno_bajo_d[0] <= _001_[0];
  (* src = "FSM_synth.v:24" *)
  always @(posedge clk)
      interno_bajo_d[1] <= _001_[1];
  (* src = "FSM_synth.v:24" *)
  always @(posedge clk)
      interno_bajo_d[2] <= _001_[2];
  assign _004_ = _012_ & estado[1];
  assign _003_ = _017_ & estado[3];
  assign _005_ = _013_ & estado[1];
  assign _026_[0] = FIFO_empty[0] ^(* src = "FSM_synth.v:81" *)  1'h1;
  assign _026_[1] = FIFO_empty[1] ^(* src = "FSM_synth.v:81" *)  1'h1;
  assign _026_[2] = FIFO_empty[2] ^(* src = "FSM_synth.v:81" *)  1'h1;
  assign _026_[3] = FIFO_empty[3] ^(* src = "FSM_synth.v:81" *)  1'h1;
  assign _026_[4] = FIFO_empty[4] ^(* src = "FSM_synth.v:81" *)  1'h1;
  assign _026_[5] = FIFO_empty[5] ^(* src = "FSM_synth.v:81" *)  1'h1;
  assign _026_[6] = FIFO_empty[6] ^(* src = "FSM_synth.v:81" *)  1'h1;
  assign _026_[7] = FIFO_empty[7] ^(* src = "FSM_synth.v:81" *)  1'h1;
  assign _026_[8] = FIFO_empty[8] ^(* src = "FSM_synth.v:81" *)  1'h1;
  assign _026_[9] = FIFO_empty[9] ^(* src = "FSM_synth.v:81" *)  1'h1;
  assign _010_ = reset & estado[0];
  assign _009_ = _016_ & estado[1];
  assign _027_[1] = init ^ 1'h1;
  assign _008_ = _015_ & estado[3];
  assign _007_ = reset & estado[2];
  assign _025_[0] = reset ^ 1'h1;
  assign _025_[1] = _002_ ^ 1'h1;
  assign _006_ = _014_ & estado[3];
  assign { _027_[2], _027_[0] } = _025_;
endmodule

FSM/FSM.v
//Proyecto Circuitos Digitales II
//20-11-2021
//Módulo de la máquina de estados

module FSM (input reset,
            input clk,
            input init,
            input [2:0] umbral_alto,
            input [2:0] umbral_bajo,
            input [9:0] FIFO_empty,
            output reg idle,
            output reg [2:0] interno_alto,
            output reg [2:0] interno_bajo);

parameter RESET = 0;
parameter INIT = 1;
parameter IDLE = 2;
parameter ACTIVE = 3;
reg [2:0] estado;
reg [2:0] proximo_estado;
reg [2:0] interno_alto_d;
reg [2:0] interno_bajo_d;

always @(posedge clk) begin
    
        if (!reset)
        begin
                estado <= RESET;
                interno_alto_d <= 0;
                interno_bajo_d <= 0;
        end

        else begin
                estado <= proximo_estado;
                interno_alto_d <= interno_alto;
                interno_bajo_d <= interno_bajo;
        
        end 
        end

always @(*) begin

    proximo_estado = estado;
    idle = 0;
    interno_alto = interno_alto_d;
    interno_bajo = interno_bajo_d;

    if (init) begin
        proximo_estado = INIT;
    end

    case (estado)
        RESET: begin
                idle = 0;
                proximo_estado = INIT;
                end

        INIT: begin

                interno_alto = umbral_alto;
                interno_bajo = umbral_bajo;
                proximo_estado = IDLE;

        end

        IDLE: begin

                if (FIFO_empty == 10'b1111111111) begin
                    idle = 1;
                end

                else begin
                    idle = 0;
                    proximo_estado = ACTIVE; 
                end
                
        end

        ACTIVE: begin

                if (FIFO_empty == 10'b1111111111) begin
                   proximo_estado = IDLE; 
                end
        end
        
        default:
        proximo_estado = RESET;
        endcase

        end

endmodule

FSM/banco_FSM.v
//Proyecto II
//Desarrollo de FSM
//20-11-2012
//Version 1.0

//Banco de pruebas para memoria

// escala	unidad temporal (valor de "#1") / precisión
`timescale 	1ns	/ 100ps

// Se incluyen los archivos necesario
`include "FSM.v"
`include "FSM_synth.v"
`include "probador_FSM.v"


module banco_FSM;

    //Wires
    wire reset;
    wire clk;
    wire init;
    wire [2:0] umbral_alto;
    wire [2:0] umbral_bajo;
    wire [9:0] FIFO_empty;
    wire idle;
    wire [2:0] interno_alto;
    wire [2:0] interno_bajo;
	wire idle_synth;
    wire [2:0] interno_alto_synth;
    wire [2:0] interno_bajo_synth;
    

	// Se instancia el módulo de memoria conductual
	FSM conductual(/*AUTOINST*/
		       // Outputs
		       .idle		(idle),
		       .interno_alto	(interno_alto[2:0]),
		       .interno_bajo	(interno_bajo[2:0]),
		       // Inputs
		       .reset		(reset),
		       .clk		(clk),
		       .init		(init),
		       .umbral_alto	(umbral_alto[2:0]),
		       .umbral_bajo	(umbral_bajo[2:0]),
		       .FIFO_empty	(FIFO_empty[9:0]));

    FSM_synth estructural(/*AUTOINST*/
			  // Outputs
			  .idle			(idle_synth),
			  .interno_alto		(interno_alto_synth[2:0]),
			  .interno_bajo		(interno_bajo_synth[2:0]),
			  // Inputs
			  .FIFO_empty		(FIFO_empty[9:0]),
			  .clk			(clk),
			  .init			(init),
			  .reset		(reset),
			  .umbral_alto		(umbral_alto[2:0]),
			  .umbral_bajo		(umbral_bajo[2:0]));

	// Probador
	probador_FSM probador(/*AUTOINST*/
			      // Outputs
			      .reset		(reset),
			      .clk		(clk),
			      .init		(init),
			      .umbral_alto	(umbral_alto[2:0]),
			      .umbral_bajo	(umbral_bajo[2:0]),
			      .FIFO_empty	(FIFO_empty[9:0]),
			      // Inputs
			      .idle		(idle),
			      .interno_alto	(interno_alto[2:0]),
			      .interno_bajo	(interno_bajo[2:0]));

endmodule

FSM/FSM.vcd
$date
	Tue Nov 23 18:10:10 2021
$end
$version
	Icarus Verilog
$end
$timescale
	100ps
$end
$scope module banco_FSM $end
$var wire 3 ! umbral_bajo [2:0] $end
$var wire 3 " umbral_alto [2:0] $end
$var wire 1 # reset $end
$var wire 3 $ interno_bajo_synth [2:0] $end
$var wire 3 % interno_bajo [2:0] $end
$var wire 3 & interno_alto_synth [2:0] $end
$var wire 3 ' interno_alto [2:0] $end
$var wire 1 ( init $end
$var wire 1 ) idle_synth $end
$var wire 1 * idle $end
$var wire 1 + clk $end
$var wire 10 , FIFO_empty [9:0] $end
$scope module conductual $end
$var wire 3 - umbral_bajo [2:0] $end
$var wire 3 . umbral_alto [2:0] $end
$var wire 1 # reset $end
$var wire 1 ( init $end
$var wire 1 + clk $end
$var wire 10 / FIFO_empty [9:0] $end
$var reg 3 0 estado [2:0] $end
$var reg 1 * idle $end
$var reg 3 1 interno_alto [2:0] $end
$var reg 3 2 interno_alto_d [2:0] $end
$var reg 3 3 interno_bajo [2:0] $end
$var reg 3 4 interno_bajo_d [2:0] $end
$var reg 3 5 proximo_estado [2:0] $end
$upscope $end
$scope module estructural $end
$var wire 1 6 _002_ $end
$var wire 1 7 _003_ $end
$var wire 1 8 _004_ $end
$var wire 1 9 _005_ $end
$var wire 1 : _006_ $end
$var wire 1 ; _007_ $end
$var wire 1 < _008_ $end
$var wire 1 = _009_ $end
$var wire 1 > _010_ $end
$var wire 1 ? _012_ $end
$var wire 1 @ _013_ $end
$var wire 1 A _014_ $end
$var wire 1 B _015_ $end
$var wire 1 C _016_ $end
$var wire 1 D _017_ $end
$var wire 1 E _018_ $end
$var wire 1 F _021_ $end
$var wire 1 G _022_ $end
$var wire 1 H _023_ $end
$var wire 1 I _024_ $end
$var wire 1 J _028_ $end
$var wire 1 K _029_ $end
$var wire 1 L _030_ $end
$var wire 1 M _031_ $end
$var wire 1 N _032_ $end
$var wire 1 O _033_ $end
$var wire 1 P _034_ $end
$var wire 3 Q umbral_bajo [2:0] $end
$var wire 3 R umbral_alto [2:0] $end
$var wire 1 # reset $end
$var wire 3 S interno_bajo [2:0] $end
$var wire 3 T interno_alto [2:0] $end
$var wire 1 ( init $end
$var wire 1 ) idle $end
$var wire 1 + clk $end
$var wire 3 U _027_ [2:0] $end
$var wire 10 V _026_ [9:0] $end
$var wire 2 W _025_ [1:0] $end
$var wire 2 X _020_ [1:0] $end
$var wire 5 Y _019_ [4:0] $end
$var wire 4 Z _011_ [3:0] $end
$var wire 3 [ _001_ [2:0] $end
$var wire 3 \ _000_ [2:0] $end
$var wire 10 ] FIFO_empty [9:0] $end
$var reg 4 ^ estado [3:0] $end
$var reg 3 _ interno_alto_d [2:0] $end
$var reg 3 ` interno_bajo_d [2:0] $end
$upscope $end
$scope module probador $end
$var wire 1 * idle $end
$var wire 3 a interno_alto [2:0] $end
$var wire 3 b interno_bajo [2:0] $end
$var reg 10 c FIFO_empty [9:0] $end
$var reg 1 + clk $end
$var reg 1 ( init $end
$var reg 1 # reset $end
$var reg 3 d umbral_alto [2:0] $end
$var reg 3 e umbral_bajo [2:0] $end
$upscope $end
$upscope $end
$enddefinitions $end
#0
$dumpvars
b1 e
b101 d
b1111111111 c
bx b
bx a
bx `
bx _
bx ^
b1111111111 ]
b0 \
b0 [
b1 Z
b0 Y
b0 X
b1 W
b0 V
b11 U
bx T
bx S
b101 R
b1 Q
1P
1O
1N
0M
1L
1K
1J
0I
1H
0G
0F
1E
0D
0C
0B
0A
0@
0?
0>
0=
0<
0;
0:
09
08
07
16
b0 5
bx 4
bx 3
bx 2
bx 1
bx 0
b1111111111 /
b101 .
b1 -
b1111111111 ,
0+
0*
x)
0(
bx '
bx &
bx %
bx $
0#
b101 "
b1 !
$end
#10
0)
b0 &
b0 T
b0 $
b0 S
b1 5
b0 %
b0 3
b0 b
b0 '
b0 1
b0 a
b0 4
b0 2
b0 0
b1 ^
b0 _
b0 `
1+
#20
0+
#30
1@
0P
1A
0E
0J
b10 U
1G
b1 5
b0 W
1>
b100 Z
b110 "
b110 .
b110 R
b110 d
b11 !
b11 -
b11 Q
b11 e
1#
1+
#40
0+
#50
b11 [
b110 \
b10 Z
0G
1I
0>
b11 $
b11 S
b110 &
b110 T
1;
b10 5
b11 %
b11 3
b11 b
b110 '
b110 1
b110 a
b1 0
b100 ^
1+
#60
0+
#70
0I
0;
1)
19
1*
b11 `
b110 _
b10 ^
b11 4
b110 2
b10 0
1+
#80
0+
#90
1+
#100
0+
#110
09
0@
0A
b1000 Z
1P
1J
18
b110 U
1D
1?
b10 W
0)
0L
0K
1F
06
1M
b11 X
b11111 Y
b1111111110 V
b11 5
0*
b1 ,
b1 /
b1 ]
b1 c
1+
#120
0+
#130
08
17
b11 0
b1000 ^
b111 "
b111 .
b111 R
b111 d
b10 !
b10 -
b10 Q
b10 e
1+
#140
0+
#150
1+
#160
0+
#170
1+
#180
0+
#190
1<
1B
b100 Z
0O
07
0H
0D
1L
b100 U
1E
b1 5
1(
1+
#200
0+
#210
b10 [
b111 \
1I
b10 $
b10 S
b111 &
b111 T
1;
b10 %
b10 3
b10 b
b111 '
b111 1
b111 a
b1 0
b100 ^
0<
0B
b10 Z
1O
07
1H
1D
0L
b110 U
0E
b10 5
0(
1+
#220
0+
#230
0I
b1000 Z
0;
18
b11 5
b10 `
b111 _
b10 ^
b10 4
b111 2
b10 0
1+
#240
0+
#250
08
17
b11 0
b1000 ^
1+
