FSM/probador_FSM.v
//Proyecto II
//Desarrollo de FSM
//20-11-2012
//Version 1.0

//Probador

module probador_FSM (output reg reset,
            output reg clk,
            output reg init,
            output reg [2:0] umbral_alto,
            output reg [2:0] umbral_bajo,
            output reg [9:0] FIFO_empty,
            input idle,
            input [2:0] interno_alto,
            input [2:0] interno_bajo);

    initial begin
        reset <= 0;
        init <= 0;
        umbral_alto <= 5;
        clk <= 0;
        umbral_bajo <= 1;
        FIFO_empty <= 10'b1111111111;
    end
    always #1 clk <= ~clk;

	initial begin
	$dumpfile("FSM.vcd");
	$dumpvars;

    @(posedge clk);
    @(posedge clk);
    reset <= 1;
    umbral_bajo <= 3;
    umbral_alto <= 6;
    @(posedge clk);
    @(posedge clk);
    @(posedge clk);
    @(posedge clk);
    FIFO_empty <= 1;
    @(posedge clk);
    umbral_bajo <= 2;
    umbral_alto <= 7;
    @(posedge clk);
    @(posedge clk);
    @(posedge clk);
    init = 1;
    @(posedge clk);
    init = 0;
    @(posedge clk);
    @(posedge clk);

	#3 $finish;
    
	end

endmodule

FSM/FSM_synth.v
/* Generated by Yosys 0.9 (git sha1 1979e0b) */

(* top =  1  *)
(* src = "FSM_synth.v:5" *)
module FSM_synth(reset, clk, init, umbral_alto, umbral_bajo, FIFO_empty, idle, interno_alto, interno_bajo);
  (* src = "FSM_synth.v:25" *)
  wire [2:0] _00_;
  (* src = "FSM_synth.v:33" *)
  wire _01_;
  (* src = "FSM_synth.v:33" *)
  wire [2:0] _02_;
  wire _03_;
  wire _04_;
  wire _05_;
  wire _06_;
  wire _07_;
  wire _08_;
  wire _09_;
  wire _10_;
  wire _11_;
  wire _12_;
  wire _13_;
  wire _14_;
  wire [4:0] _15_;
  wire [1:0] _16_;
  wire _17_;
  wire _18_;
  wire _19_;
  wire _20_;
  wire _21_;
  wire _22_;
  wire _23_;
  wire [9:0] _24_;
  wire [2:0] _25_;
  wire _26_;
  wire _27_;
  (* src = "FSM_synth.v:66|FSM.v:39|<techmap.v>:432" *)
  wire [8:0] _28_;
  (* src = "FSM_synth.v:66|FSM.v:39|<techmap.v>:428" *)
  wire [2:0] _29_;
  wire _30_;
  (* src = "FSM_synth.v:66|FSM.v:39|<techmap.v>:445" *)
  wire _31_;
  (* src = "FSM_synth.v:10" *)
  input [9:0] FIFO_empty;
  (* src = "FSM_synth.v:6" *)
  input clk;
  (* init = 3'h0 *)
  (* src = "FSM_synth.v:22" *)
  reg [2:0] estado = 3'h0;
  (* init = 1'h0 *)
  (* src = "FSM_synth.v:11" *)
  output idle;
  (* src = "FSM_synth.v:7" *)
  input init;
  (* init = 3'h6 *)
  (* src = "FSM_synth.v:12" *)
  output [2:0] interno_alto;
  (* init = 3'h2 *)
  (* src = "FSM_synth.v:13" *)
  output [2:0] interno_bajo;
  (* init = 3'h0 *)
  (* src = "FSM_synth.v:23" *)
  wire [2:0] proximo_estado;
  (* src = "FSM_synth.v:5" *)
  input reset;
  (* src = "FSM_synth.v:8" *)
  input [2:0] umbral_alto;
  (* src = "FSM_synth.v:9" *)
  input [2:0] umbral_bajo;
  assign _15_[0] = _24_[0] |(* src = "FSM_synth.v:68" *)  _24_[1];
  assign _15_[1] = _24_[2] |(* src = "FSM_synth.v:68" *)  _24_[3];
  assign _15_[2] = _24_[4] |(* src = "FSM_synth.v:68" *)  _24_[5];
  assign _15_[3] = _24_[6] |(* src = "FSM_synth.v:68" *)  _24_[7];
  assign _15_[4] = _24_[8] |(* src = "FSM_synth.v:68" *)  _24_[9];
  assign _16_[0] = _15_[0] |(* src = "FSM_synth.v:68" *)  _15_[1];
  assign _16_[1] = _15_[2] |(* src = "FSM_synth.v:68" *)  _15_[3];
  assign _17_ = _16_[0] |(* src = "FSM_synth.v:68" *)  _16_[1];
  assign _09_ = _17_ |(* src = "FSM_synth.v:68" *)  _15_[4];
  assign _18_ = _25_[0] |(* src = "FSM_synth.v:66|FSM.v:39" *)  _25_[1];
  assign _26_ = _18_ |(* src = "FSM_synth.v:66|FSM.v:39" *)  estado[2];
  assign _19_ = _25_[0] |(* src = "FSM_synth.v:45|FSM.v:39" *)  estado[1];
  assign _27_ = _19_ |(* src = "FSM_synth.v:45|FSM.v:39" *)  estado[2];
  assign _20_ = estado[0] |(* src = "FSM_synth.v:53|FSM.v:39" *)  _25_[1];
  assign _06_ = _20_ |(* src = "FSM_synth.v:53|FSM.v:39" *)  estado[2];
  assign _03_ = _08_ | _30_;
  assign _11_ = _13_ |(* src = "FSM_synth.v:33" *)  _14_;
  assign _21_ = _03_ |(* src = "FSM_synth.v:66|FSM.v:39|<techmap.v>:441" *)  _22_;
  assign _29_[0] = _22_ |(* src = "FSM_synth.v:66|FSM.v:39|<techmap.v>:441" *)  _28_[6];
  assign _31_ = _21_ |(* src = "FSM_synth.v:66|FSM.v:39|<techmap.v>:445" *)  _28_[6];
  assign _23_ = estado[0] |(* src = "FSM_synth.v:40|FSM.v:39" *)  estado[1];
  assign _05_ = _23_ |(* src = "FSM_synth.v:40|FSM.v:39" *)  estado[2];
  assign _10_ = ~(* src = "FSM_synth.v:68" *) _09_;
  assign _30_ = ~(* src = "FSM_synth.v:66|FSM.v:39" *) _26_;
  assign _28_[6] = ~(* src = "FSM_synth.v:40|FSM.v:39" *) _05_;
  assign _08_ = ~(* src = "FSM_synth.v:45|FSM.v:39" *) _27_;
  assign _22_ = ~(* src = "FSM_synth.v:53|FSM.v:39" *) _06_;
  assign _01_ = _06_ ? (* src = "FSM_synth.v:53|FSM.v:39" *) 1'h0 : _10_;
  assign _00_[0] = reset ? (* src = "FSM_synth.v:27" *) proximo_estado[0] : 1'h0;
  assign _00_[1] = reset ? (* src = "FSM_synth.v:27" *) proximo_estado[1] : 1'h0;
  assign _00_[2] = reset ? (* src = "FSM_synth.v:27" *) proximo_estado[2] : 1'h0;
  assign _02_[0] = _31_ ? (* src = "FSM_synth.v:66|FSM.v:39|<techmap.v>:445" *) _29_[0] : 1'h0;
  assign _02_[1] = _31_ ? (* src = "FSM_synth.v:66|FSM.v:39|<techmap.v>:445" *) _21_ : 1'h0;
  assign _07_ = ~_12_;
  assign _04_ = ~_11_;
  (* src = "FSM_synth.v:25" *)
  always @(posedge clk)
      estado[0] <= _00_[0];
  (* src = "FSM_synth.v:25" *)
  always @(posedge clk)
      estado[1] <= _00_[1];
  (* src = "FSM_synth.v:25" *)
  always @(posedge clk)
      estado[2] <= _00_[2];
  (* src = "FSM_synth.v:33" *)
  \$_DLATCH_P_  _70_ (
    .D(_01_),
    .E(_07_),
    .Q(idle)
  );
  (* src = "FSM_synth.v:33" *)
  \$_DLATCH_P_  _71_ (
    .D(umbral_alto[0]),
    .E(_08_),
    .Q(interno_alto[0])
  );
  (* src = "FSM_synth.v:33" *)
  \$_DLATCH_P_  _72_ (
    .D(umbral_alto[1]),
    .E(_08_),
    .Q(interno_alto[1])
  );
  (* src = "FSM_synth.v:33" *)
  \$_DLATCH_P_  _73_ (
    .D(umbral_alto[2]),
    .E(_08_),
    .Q(interno_alto[2])
  );
  (* src = "FSM_synth.v:33" *)
  \$_DLATCH_P_  _74_ (
    .D(umbral_bajo[0]),
    .E(_08_),
    .Q(interno_bajo[0])
  );
  (* src = "FSM_synth.v:33" *)
  \$_DLATCH_P_  _75_ (
    .D(umbral_bajo[1]),
    .E(_08_),
    .Q(interno_bajo[1])
  );
  (* src = "FSM_synth.v:33" *)
  \$_DLATCH_P_  _76_ (
    .D(umbral_bajo[2]),
    .E(_08_),
    .Q(interno_bajo[2])
  );
  (* src = "FSM_synth.v:33" *)
  \$_DLATCH_P_  _77_ (
    .D(_02_[0]),
    .E(_04_),
    .Q(proximo_estado[0])
  );
  (* src = "FSM_synth.v:33" *)
  \$_DLATCH_P_  _78_ (
    .D(_02_[1]),
    .E(_04_),
    .Q(proximo_estado[1])
  );
  (* src = "FSM_synth.v:33" *)
  \$_DLATCH_P_  _79_ (
    .D(1'h0),
    .E(_04_),
    .Q(proximo_estado[2])
  );
  assign _24_[0] = FIFO_empty[0] ^(* src = "FSM_synth.v:68" *)  1'h1;
  assign _24_[1] = FIFO_empty[1] ^(* src = "FSM_synth.v:68" *)  1'h1;
  assign _24_[2] = FIFO_empty[2] ^(* src = "FSM_synth.v:68" *)  1'h1;
  assign _24_[3] = FIFO_empty[3] ^(* src = "FSM_synth.v:68" *)  1'h1;
  assign _24_[4] = FIFO_empty[4] ^(* src = "FSM_synth.v:68" *)  1'h1;
  assign _24_[5] = FIFO_empty[5] ^(* src = "FSM_synth.v:68" *)  1'h1;
  assign _24_[6] = FIFO_empty[6] ^(* src = "FSM_synth.v:68" *)  1'h1;
  assign _24_[7] = FIFO_empty[7] ^(* src = "FSM_synth.v:68" *)  1'h1;
  assign _24_[8] = FIFO_empty[8] ^(* src = "FSM_synth.v:68" *)  1'h1;
  assign _24_[9] = FIFO_empty[9] ^(* src = "FSM_synth.v:68" *)  1'h1;
  assign _25_[0] = estado[0] ^(* src = "FSM_synth.v:45|FSM.v:39" *)  1'h1;
  assign _25_[1] = estado[1] ^(* src = "FSM_synth.v:53|FSM.v:39" *)  1'h1;
  assign _12_ = _05_ &(* src = "FSM_synth.v:33" *)  _06_;
  assign _14_ = _30_ &(* src = "FSM_synth.v:33" *)  _09_;
  assign _13_ = _22_ &(* src = "FSM_synth.v:33" *)  _10_;
  assign _02_[2] = 1'h0;
  assign _25_[2] = estado[2];
  assign { _28_[8:7], _28_[5:0] } = { 3'h0, _22_, _22_, 1'h0, _03_, 1'h0 };
  assign _29_[2:1] = { 1'h0, _21_ };
endmodule

capa_transaccion/FSM.v
//Proyecto Circuitos Digitales II
//20-11-2021
//Módulo de la máquina de estados

module FSM (input reset,
            input clk,
            input init,
            input [2:0] umbral_alto,
            input [2:0] umbral_bajo,
            input [9:0] FIFO_empty,
            output reg idle,
            output reg [2:0] interno_alto,
            output reg [2:0] interno_bajo);

initial interno_alto = 6;
initial interno_bajo = 2;
initial idle = 0;
parameter RESET = 0;
parameter INIT = 1;
parameter IDLE = 2;
parameter ACTIVE = 3;
reg [2:0] estado = 0;
reg [2:0] proximo_estado = 0;

always @(posedge clk) begin
    
        if (!reset) estado <= RESET;
        else begin
                estado <= proximo_estado;
        end 
        end

always @(*) begin

    if (init) begin
        proximo_estado <= INIT;
    end

    case (estado)
        RESET: begin
                idle <= 0;
                proximo_estado <= INIT;
                end

        INIT: begin

                interno_alto <= umbral_alto;
                interno_bajo <= umbral_bajo;
                proximo_estado <= IDLE;

        end

        IDLE: begin

                if (FIFO_empty == 10'b1111111111) begin
                    idle <= 1;
                end

                else begin
                    idle <= 0;
                    proximo_estado <= ACTIVE; 
                end
                
        end

        ACTIVE: begin

                if (FIFO_empty == 10'b1111111111) begin
                   proximo_estado <= IDLE; 
                end
        end
        
        default:
        proximo_estado = RESET;
        endcase

        end

endmodule

FSM/banco_FSM.v
//Proyecto II
//Desarrollo de FSM
//20-11-2012
//Version 1.0

//Banco de pruebas para memoria

// escala	unidad temporal (valor de "#1") / precisión
`timescale 	1ns	/ 100ps

// Se incluyen los archivos necesario
`include "FSM.v"
`include "FSM_synth.v"
`include "probador_FSM.v"


module banco_FSM;

    //Wires
    wire reset;
    wire clk;
    wire init;
    wire [2:0] umbral_alto;
    wire [2:0] umbral_bajo;
    wire [9:0] FIFO_empty;
    wire idle;
    wire [2:0] interno_alto;
    wire [2:0] interno_bajo;
    

	// Se instancia el módulo de memoria conductual
	FSM conductual(/*AUTOINST*/
		       // Outputs
		       .idle		(idle),
		       .interno_alto	(interno_alto[2:0]),
		       .interno_bajo	(interno_bajo[2:0]),
		       // Inputs
		       .reset		(reset),
		       .clk		(clk),
		       .init		(init),
		       .umbral_alto	(umbral_alto[2:0]),
		       .umbral_bajo	(umbral_bajo[2:0]),
		       .FIFO_empty	(FIFO_empty[9:0]));

    FSM_synth estructural(/*AUTOINST*/
			  // Outputs
			  .idle			(idle),
			  .interno_alto		(interno_alto[2:0]),
			  .interno_bajo		(interno_bajo[2:0]),
			  // Inputs
			  .FIFO_empty		(FIFO_empty[9:0]),
			  .clk			(clk),
			  .init			(init),
			  .reset		(reset),
			  .umbral_alto		(umbral_alto[2:0]),
			  .umbral_bajo		(umbral_bajo[2:0]));

	// Probador
	probador_FSM probador(/*AUTOINST*/
			      // Outputs
			      .reset		(reset),
			      .clk		(clk),
			      .init		(init),
			      .umbral_alto	(umbral_alto[2:0]),
			      .umbral_bajo	(umbral_bajo[2:0]),
			      .FIFO_empty	(FIFO_empty[9:0]),
			      // Inputs
			      .idle		(idle),
			      .interno_alto	(interno_alto[2:0]),
			      .interno_bajo	(interno_bajo[2:0]));

endmodule

FSM/FSM.vcd
$date
	Sat Nov 20 20:46:47 2021
$end
$version
	Icarus Verilog
$end
$timescale
	100ps
$end
$scope module banco_FSM $end
$var wire 3 ! umbral_bajo [2:0] $end
$var wire 3 " umbral_alto [2:0] $end
$var wire 1 # reset $end
$var wire 3 $ interno_bajo [2:0] $end
$var wire 3 % interno_alto [2:0] $end
$var wire 1 & init $end
$var wire 1 ' idle $end
$var wire 1 ( clk $end
$var wire 10 ) FIFO_empty [9:0] $end
$scope module conductual $end
$var wire 3 * umbral_bajo [2:0] $end
$var wire 3 + umbral_alto [2:0] $end
$var wire 1 # reset $end
$var wire 1 & init $end
$var wire 1 ( clk $end
$var wire 10 , FIFO_empty [9:0] $end
$var reg 3 - estado [2:0] $end
$var reg 1 ' idle $end
$var reg 3 . interno_alto [2:0] $end
$var reg 3 / interno_bajo [2:0] $end
$var reg 3 0 proximo_estado [2:0] $end
$upscope $end
$scope module probador $end
$var wire 1 ' idle $end
$var wire 3 1 interno_alto [2:0] $end
$var wire 3 2 interno_bajo [2:0] $end
$var reg 10 3 FIFO_empty [9:0] $end
$var reg 1 ( clk $end
$var reg 1 & init $end
$var reg 1 # reset $end
$var reg 3 4 umbral_alto [2:0] $end
$var reg 3 5 umbral_bajo [2:0] $end
$upscope $end
$upscope $end
$enddefinitions $end
#0
$dumpvars
b1 5
b101 4
b1111111111 3
b10 2
b110 1
b1 0
b10 /
b110 .
b0 -
b1111111111 ,
b101 +
b1 *
b1111111111 )
0(
0'
0&
b110 %
b10 $
0#
b101 "
b1 !
$end
#10
1(
#20
0(
#30
b110 "
b110 +
b110 4
b11 !
b11 *
b11 5
1#
1(
#40
0(
#50
b10 0
b11 $
b11 /
b11 2
b1 -
1(
#60
0(
#70
1'
b10 -
1(
#80
0(
#90
1(
#100
0(
#110
b11 0
0'
b1 )
b1 ,
b1 3
1(
#120
0(
#130
b11 -
b111 "
b111 +
b111 4
b10 !
b10 *
b10 5
1(
#140
0(
#150
1(
#160
0(
#170
1(
#180
0(
#190
b1 0
1&
1(
#200
0(
#210
b10 0
b10 $
b10 /
b10 2
b111 %
b111 .
b111 1
b1 -
0&
1(
#220
0(
#230
b11 0
b10 -
1(
#240
0(
#250
b11 -
1(
