FSM/probador_FSM.v
//Proyecto II
//Desarrollo de FSM
//20-11-2012
//Version 1.0

//Probador

module probador_FSM (output reg reset,
            output reg clk,
            output reg init,
            output reg [2:0] umbral_alto,
            output reg [2:0] umbral_bajo,
            output reg [9:0] FIFO_empty,
            input idle,
            input [2:0] interno_alto,
            input [2:0] interno_bajo);

    initial begin
        reset <= 0;
        init <= 0;
        umbral_alto <= 5;
        clk <= 0;
        umbral_bajo <= 1;
        FIFO_empty <= 10'b1111111111;
    end
    always #1 clk <= ~clk;

	initial begin
	$dumpfile("FSM.vcd");
	$dumpvars;

    @(posedge clk);
    @(posedge clk);
    reset <= 1;
    umbral_bajo <= 3;
    umbral_alto <= 6;
    @(posedge clk);
    @(posedge clk);
    @(posedge clk);
    @(posedge clk);
    FIFO_empty <= 1;
    @(posedge clk);
    umbral_bajo <= 2;
    umbral_alto <= 7;
    @(posedge clk);
    @(posedge clk);
    @(posedge clk);
    init = 1;
    @(posedge clk);
    init = 0;
    @(posedge clk);
    @(posedge clk);

	#3 $finish;
    
	end

endmodule

FSM/FSM_synth.v
/* Generated by Yosys 0.9 (git sha1 1979e0b) */

(* top =  1  *)
(* src = "FSM_synth.v:5" *)
module FSM_synth(reset, clk, init, umbral_alto, umbral_bajo, FIFO_empty, idle, interno_alto, interno_bajo);
  (* src = "FSM_synth.v:25" *)
  wire [2:0] _000_;
  (* src = "FSM_synth.v:33" *)
  wire [2:0] _001_;
  (* src = "FSM_synth.v:33" *)
  wire _002_;
  (* src = "FSM_synth.v:33" *)
  wire [2:0] _003_;
  (* src = "FSM_synth.v:33" *)
  wire [2:0] _004_;
  wire [4:0] _005_;
  wire [1:0] _006_;
  wire _007_;
  wire _008_;
  wire _009_;
  wire _010_;
  wire [1:0] _011_;
  wire [1:0] _012_;
  wire [1:0] _013_;
  wire [1:0] _014_;
  wire _015_;
  wire _016_;
  wire [9:0] _017_;
  wire [2:0] _018_;
  wire _019_;
  wire _020_;
  wire _021_;
  wire _022_;
  wire _023_;
  wire _024_;
  (* src = "FSM_synth.v:71|FSM.v:44|<techmap.v>:432" *)
  wire [11:0] _025_;
  (* src = "FSM_synth.v:71|FSM.v:44|<techmap.v>:428" *)
  wire [2:0] _026_;
  (* src = "FSM_synth.v:71|FSM.v:44|<techmap.v>:445" *)
  wire _027_;
  (* src = "FSM_synth.v:10" *)
  input [9:0] FIFO_empty;
  (* src = "FSM_synth.v:6" *)
  input clk;
  (* init = 3'h0 *)
  (* src = "FSM_synth.v:20" *)
  reg [2:0] estado = 3'h0;
  (* init = 1'h0 *)
  (* src = "FSM_synth.v:11" *)
  output idle;
  (* src = "FSM_synth.v:7" *)
  input init;
  (* src = "FSM_synth.v:12" *)
  output [2:0] interno_alto;
  (* src = "FSM_synth.v:13" *)
  output [2:0] interno_bajo;
  (* init = 3'h0 *)
  (* src = "FSM_synth.v:21" *)
  wire [2:0] proximo_estado;
  (* src = "FSM_synth.v:5" *)
  input reset;
  (* src = "FSM_synth.v:22" *)
  wire [2:0] thr_alto;
  (* src = "FSM_synth.v:23" *)
  wire [2:0] thr_bajo;
  (* src = "FSM_synth.v:8" *)
  input [2:0] umbral_alto;
  (* src = "FSM_synth.v:9" *)
  input [2:0] umbral_bajo;
  assign _005_[0] = _017_[0] |(* src = "FSM_synth.v:73" *)  _017_[1];
  assign _005_[1] = _017_[2] |(* src = "FSM_synth.v:73" *)  _017_[3];
  assign _005_[2] = _017_[4] |(* src = "FSM_synth.v:73" *)  _017_[5];
  assign _005_[3] = _017_[6] |(* src = "FSM_synth.v:73" *)  _017_[7];
  assign _005_[4] = _017_[8] |(* src = "FSM_synth.v:73" *)  _017_[9];
  assign _006_[0] = _005_[0] |(* src = "FSM_synth.v:73" *)  _005_[1];
  assign _006_[1] = _005_[2] |(* src = "FSM_synth.v:73" *)  _005_[3];
  assign _007_ = _006_[0] |(* src = "FSM_synth.v:73" *)  _006_[1];
  assign _019_ = _007_ |(* src = "FSM_synth.v:73" *)  _005_[4];
  assign _008_ = _018_[0] |(* src = "FSM_synth.v:71|FSM.v:44" *)  _018_[1];
  assign _020_ = _008_ |(* src = "FSM_synth.v:71|FSM.v:44" *)  estado[2];
  assign _009_ = estado[0] |(* src = "FSM_synth.v:58|FSM.v:44" *)  _018_[1];
  assign _021_ = _009_ |(* src = "FSM_synth.v:58|FSM.v:44" *)  estado[2];
  assign _010_ = _018_[0] |(* src = "FSM_synth.v:50|FSM.v:44" *)  estado[1];
  assign _022_ = _010_ |(* src = "FSM_synth.v:50|FSM.v:44" *)  estado[2];
  assign _011_[0] = _025_[2] |(* src = "FSM_synth.v:71|FSM.v:44|<techmap.v>:441" *)  _025_[5];
  assign _012_[0] = _025_[1] |(* src = "FSM_synth.v:71|FSM.v:44|<techmap.v>:441" *)  _025_[4];
  assign _026_[1] = _012_[0] |(* src = "FSM_synth.v:71|FSM.v:44|<techmap.v>:441" *)  _012_[1];
  assign _013_[0] = _025_[0] |(* src = "FSM_synth.v:71|FSM.v:44|<techmap.v>:441" *)  _025_[3];
  assign _026_[0] = _013_[0] |(* src = "FSM_synth.v:71|FSM.v:44|<techmap.v>:441" *)  _013_[1];
  assign _014_[0] = _023_ |(* src = "FSM_synth.v:71|FSM.v:44|<techmap.v>:445" *)  _024_;
  assign _014_[1] = _012_[1] |(* src = "FSM_synth.v:71|FSM.v:44|<techmap.v>:445" *)  _013_[1];
  assign _027_ = _014_[0] |(* src = "FSM_synth.v:71|FSM.v:44|<techmap.v>:445" *)  _014_[1];
  assign _015_ = estado[0] |(* src = "FSM_synth.v:45|FSM.v:44" *)  estado[1];
  assign _016_ = _015_ |(* src = "FSM_synth.v:45|FSM.v:44" *)  estado[2];
  assign _002_ = ~(* src = "FSM_synth.v:73" *) _019_;
  assign _023_ = ~(* src = "FSM_synth.v:71|FSM.v:44" *) _020_;
  assign _013_[1] = ~(* src = "FSM_synth.v:45|FSM.v:44" *) _016_;
  assign _024_ = ~(* src = "FSM_synth.v:58|FSM.v:44" *) _021_;
  assign _012_[1] = ~(* src = "FSM_synth.v:50|FSM.v:44" *) _022_;
  assign _004_[0] = _019_ ? (* src = "FSM_synth.v:73" *) _001_[0] : 1'h0;
  assign _004_[1] = _019_ ? (* src = "FSM_synth.v:73" *) _001_[1] : 1'h1;
  assign _004_[2] = _019_ ? (* src = "FSM_synth.v:73" *) _001_[2] : 1'h0;
  assign _003_[0] = _019_ ? (* src = "FSM_synth.v:60" *) 1'h1 : _001_[0];
  assign _003_[1] = _019_ ? (* src = "FSM_synth.v:60" *) 1'h1 : _001_[1];
  assign _003_[2] = _019_ ? (* src = "FSM_synth.v:60" *) 1'h0 : _001_[2];
  assign idle = _021_ ? (* src = "FSM_synth.v:58|FSM.v:44" *) 1'h0 : _002_;
  assign interno_bajo[0] = _022_ ? (* src = "FSM_synth.v:50|FSM.v:44" *) 1'h0 : umbral_bajo[0];
  assign interno_bajo[1] = _022_ ? (* src = "FSM_synth.v:50|FSM.v:44" *) 1'h1 : umbral_bajo[1];
  assign interno_bajo[2] = _022_ ? (* src = "FSM_synth.v:50|FSM.v:44" *) 1'h0 : umbral_bajo[2];
  assign interno_alto[0] = _022_ ? (* src = "FSM_synth.v:50|FSM.v:44" *) 1'h0 : umbral_alto[0];
  assign interno_alto[1] = _022_ ? (* src = "FSM_synth.v:50|FSM.v:44" *) 1'h1 : umbral_alto[1];
  assign interno_alto[2] = _022_ ? (* src = "FSM_synth.v:50|FSM.v:44" *) 1'h1 : umbral_alto[2];
  assign _001_[0] = init ? (* src = "FSM_synth.v:40" *) 1'h1 : estado[0];
  assign _001_[1] = init ? (* src = "FSM_synth.v:40" *) 1'h0 : estado[1];
  assign _001_[2] = init ? (* src = "FSM_synth.v:40" *) 1'h0 : estado[2];
  assign _000_[0] = reset ? (* src = "FSM_synth.v:27" *) proximo_estado[0] : 1'h0;
  assign _000_[1] = reset ? (* src = "FSM_synth.v:27" *) proximo_estado[1] : 1'h0;
  assign _000_[2] = reset ? (* src = "FSM_synth.v:27" *) proximo_estado[2] : 1'h0;
  assign proximo_estado[0] = _027_ ? (* src = "FSM_synth.v:71|FSM.v:44|<techmap.v>:445" *) _026_[0] : 1'h0;
  assign proximo_estado[1] = _027_ ? (* src = "FSM_synth.v:71|FSM.v:44|<techmap.v>:445" *) _026_[1] : 1'h0;
  assign proximo_estado[2] = _027_ ? (* src = "FSM_synth.v:71|FSM.v:44|<techmap.v>:445" *) _011_[0] : 1'h0;
  (* src = "FSM_synth.v:25" *)
  always @(posedge clk)
      estado[0] <= _000_[0];
  (* src = "FSM_synth.v:25" *)
  always @(posedge clk)
      estado[1] <= _000_[1];
  (* src = "FSM_synth.v:25" *)
  always @(posedge clk)
      estado[2] <= _000_[2];
  assign _017_[0] = FIFO_empty[0] ^(* src = "FSM_synth.v:73" *)  1'h1;
  assign _017_[1] = FIFO_empty[1] ^(* src = "FSM_synth.v:73" *)  1'h1;
  assign _017_[2] = FIFO_empty[2] ^(* src = "FSM_synth.v:73" *)  1'h1;
  assign _017_[3] = FIFO_empty[3] ^(* src = "FSM_synth.v:73" *)  1'h1;
  assign _017_[4] = FIFO_empty[4] ^(* src = "FSM_synth.v:73" *)  1'h1;
  assign _017_[5] = FIFO_empty[5] ^(* src = "FSM_synth.v:73" *)  1'h1;
  assign _017_[6] = FIFO_empty[6] ^(* src = "FSM_synth.v:73" *)  1'h1;
  assign _017_[7] = FIFO_empty[7] ^(* src = "FSM_synth.v:73" *)  1'h1;
  assign _017_[8] = FIFO_empty[8] ^(* src = "FSM_synth.v:73" *)  1'h1;
  assign _017_[9] = FIFO_empty[9] ^(* src = "FSM_synth.v:73" *)  1'h1;
  assign _018_[1] = estado[1] ^(* src = "FSM_synth.v:58|FSM.v:44" *)  1'h1;
  assign _018_[0] = estado[0] ^(* src = "FSM_synth.v:50|FSM.v:44" *)  1'h1;
  assign _025_[3] = _003_[0] &(* src = "FSM_synth.v:71|FSM.v:44|<techmap.v>:434" *)  _024_;
  assign _025_[4] = _003_[1] &(* src = "FSM_synth.v:71|FSM.v:44|<techmap.v>:434" *)  _024_;
  assign _025_[5] = _003_[2] &(* src = "FSM_synth.v:71|FSM.v:44|<techmap.v>:434" *)  _024_;
  assign _025_[0] = _004_[0] &(* src = "FSM_synth.v:71|FSM.v:44|<techmap.v>:434" *)  _023_;
  assign _025_[1] = _004_[1] &(* src = "FSM_synth.v:71|FSM.v:44|<techmap.v>:434" *)  _023_;
  assign _025_[2] = _004_[2] &(* src = "FSM_synth.v:71|FSM.v:44|<techmap.v>:434" *)  _023_;
  assign _011_[1] = 1'h0;
  assign _018_[2] = estado[2];
  assign _025_[11:6] = { 2'h0, _013_[1], 1'h0, _012_[1], 1'h0 };
  assign _026_[2] = _011_[0];
  assign thr_alto = 3'h6;
  assign thr_bajo = 3'h2;
endmodule

capa_transaccion/FSM.v
//Proyecto Circuitos Digitales II
//20-11-2021
//Módulo de la máquina de estados

module FSM (input reset,
            input clk,
            input init,
            input [2:0] umbral_alto,
            input [2:0] umbral_bajo,
            input [9:0] FIFO_empty,
            output reg idle,
            output reg [2:0] interno_alto,
            output reg [2:0] interno_bajo);

initial idle = 0;
parameter RESET = 0;
parameter INIT = 1;
parameter IDLE = 2;
parameter ACTIVE = 3;
reg [2:0] estado = 0;
reg [2:0] proximo_estado = 0;
reg [2:0] thr_alto = 6;
reg [2:0] thr_bajo = 2;

always @(posedge clk) begin
    
        if (!reset) estado <= RESET;
        else begin
                estado <= proximo_estado;
        end 
        end

always @(*) begin

    proximo_estado = estado;
    idle = 0;
    interno_alto = thr_alto;
    interno_bajo = thr_bajo;

    if (init) begin
        proximo_estado = INIT;
    end

    case (estado)
        RESET: begin
                idle = 0;
                proximo_estado = INIT;
                end

        INIT: begin

                interno_alto = umbral_alto;
                interno_bajo = umbral_bajo;
                proximo_estado = IDLE;

        end

        IDLE: begin

                if (FIFO_empty == 10'b1111111111) begin
                    idle = 1;
                end

                else begin
                    idle = 0;
                    proximo_estado = ACTIVE; 
                end
                
        end

        ACTIVE: begin

                if (FIFO_empty == 10'b1111111111) begin
                   proximo_estado = IDLE; 
                end
        end
        
        default:
        proximo_estado = RESET;
        endcase

        end

endmodule

FSM/banco_FSM.v
//Proyecto II
//Desarrollo de FSM
//20-11-2012
//Version 1.0

//Banco de pruebas para memoria

// escala	unidad temporal (valor de "#1") / precisión
`timescale 	1ns	/ 100ps

// Se incluyen los archivos necesario
`include "FSM.v"
`include "FSM_synth.v"
`include "probador_FSM.v"


module banco_FSM;

    //Wires
    wire reset;
    wire clk;
    wire init;
    wire [2:0] umbral_alto;
    wire [2:0] umbral_bajo;
    wire [9:0] FIFO_empty;
    wire idle;
    wire [2:0] interno_alto;
    wire [2:0] interno_bajo;
	wire idle_synth;
    wire [2:0] interno_alto_synth;
    wire [2:0] interno_bajo_synth;
    

	// Se instancia el módulo de memoria conductual
	FSM conductual(/*AUTOINST*/
		       // Outputs
		       .idle		(idle),
		       .interno_alto	(interno_alto[2:0]),
		       .interno_bajo	(interno_bajo[2:0]),
		       // Inputs
		       .reset		(reset),
		       .clk		(clk),
		       .init		(init),
		       .umbral_alto	(umbral_alto[2:0]),
		       .umbral_bajo	(umbral_bajo[2:0]),
		       .FIFO_empty	(FIFO_empty[9:0]));

    FSM_synth estructural(/*AUTOINST*/
			  // Outputs
			  .idle			(idle_synth),
			  .interno_alto		(interno_alto_synth[2:0]),
			  .interno_bajo		(interno_bajo_synth[2:0]),
			  // Inputs
			  .FIFO_empty		(FIFO_empty[9:0]),
			  .clk			(clk),
			  .init			(init),
			  .reset		(reset),
			  .umbral_alto		(umbral_alto[2:0]),
			  .umbral_bajo		(umbral_bajo[2:0]));

	// Probador
	probador_FSM probador(/*AUTOINST*/
			      // Outputs
			      .reset		(reset),
			      .clk		(clk),
			      .init		(init),
			      .umbral_alto	(umbral_alto[2:0]),
			      .umbral_bajo	(umbral_bajo[2:0]),
			      .FIFO_empty	(FIFO_empty[9:0]),
			      // Inputs
			      .idle		(idle),
			      .interno_alto	(interno_alto[2:0]),
			      .interno_bajo	(interno_bajo[2:0]));

endmodule

FSM/FSM.vcd
$date
	Mon Nov 22 21:56:39 2021
$end
$version
	Icarus Verilog
$end
$timescale
	100ps
$end
$scope module banco_FSM $end
$var wire 3 ! umbral_bajo [2:0] $end
$var wire 3 " umbral_alto [2:0] $end
$var wire 1 # reset $end
$var wire 3 $ interno_bajo_synth [2:0] $end
$var wire 3 % interno_bajo [2:0] $end
$var wire 3 & interno_alto_synth [2:0] $end
$var wire 3 ' interno_alto [2:0] $end
$var wire 1 ( init $end
$var wire 1 ) idle_synth $end
$var wire 1 * idle $end
$var wire 1 + clk $end
$var wire 10 , FIFO_empty [9:0] $end
$scope module conductual $end
$var wire 3 - umbral_bajo [2:0] $end
$var wire 3 . umbral_alto [2:0] $end
$var wire 1 # reset $end
$var wire 1 ( init $end
$var wire 1 + clk $end
$var wire 10 / FIFO_empty [9:0] $end
$var reg 3 0 estado [2:0] $end
$var reg 1 * idle $end
$var reg 3 1 interno_alto [2:0] $end
$var reg 3 2 interno_bajo [2:0] $end
$var reg 3 3 proximo_estado [2:0] $end
$var reg 3 4 thr_alto [2:0] $end
$var reg 3 5 thr_bajo [2:0] $end
$upscope $end
$scope module estructural $end
$var wire 1 6 _002_ $end
$var wire 1 7 _007_ $end
$var wire 1 8 _008_ $end
$var wire 1 9 _009_ $end
$var wire 1 : _010_ $end
$var wire 1 ; _015_ $end
$var wire 1 < _016_ $end
$var wire 1 = _019_ $end
$var wire 1 > _020_ $end
$var wire 1 ? _021_ $end
$var wire 1 @ _022_ $end
$var wire 1 A _023_ $end
$var wire 1 B _024_ $end
$var wire 1 C _027_ $end
$var wire 3 D thr_alto [2:0] $end
$var wire 3 E thr_bajo [2:0] $end
$var wire 3 F umbral_bajo [2:0] $end
$var wire 3 G umbral_alto [2:0] $end
$var wire 1 # reset $end
$var wire 3 H proximo_estado [2:0] $end
$var wire 3 I interno_bajo [2:0] $end
$var wire 3 J interno_alto [2:0] $end
$var wire 1 ( init $end
$var wire 1 ) idle $end
$var wire 1 + clk $end
$var wire 3 K _026_ [2:0] $end
$var wire 12 L _025_ [11:0] $end
$var wire 3 M _018_ [2:0] $end
$var wire 10 N _017_ [9:0] $end
$var wire 2 O _014_ [1:0] $end
$var wire 2 P _013_ [1:0] $end
$var wire 2 Q _012_ [1:0] $end
$var wire 2 R _011_ [1:0] $end
$var wire 2 S _006_ [1:0] $end
$var wire 5 T _005_ [4:0] $end
$var wire 3 U _004_ [2:0] $end
$var wire 3 V _003_ [2:0] $end
$var wire 3 W _001_ [2:0] $end
$var wire 3 X _000_ [2:0] $end
$var wire 10 Y FIFO_empty [9:0] $end
$var reg 3 Z estado [2:0] $end
$upscope $end
$scope module probador $end
$var wire 1 * idle $end
$var wire 3 [ interno_alto [2:0] $end
$var wire 3 \ interno_bajo [2:0] $end
$var reg 10 ] FIFO_empty [9:0] $end
$var reg 1 + clk $end
$var reg 1 ( init $end
$var reg 1 # reset $end
$var reg 3 ^ umbral_alto [2:0] $end
$var reg 3 _ umbral_bajo [2:0] $end
$upscope $end
$upscope $end
$enddefinitions $end
#0
$dumpvars
b1 _
b101 ^
b1111111111 ]
b10 \
b110 [
b0 Z
b1111111111 Y
b0 X
b0 W
b0 V
b10 U
b0 T
b0 S
b0 R
b0 Q
b10 P
b10 O
b0 N
b11 M
b1000000000 L
b1 K
b110 J
b10 I
b1 H
b101 G
b1 F
b10 E
b110 D
1C
0B
0A
1@
1?
1>
0=
0<
0;
1:
19
18
07
16
b10 5
b110 4
b1 3
b10 2
b110 1
b0 0
b1111111111 /
b101 .
b1 -
b1111111111 ,
0+
0*
0)
0(
b110 '
b110 &
b10 %
b10 $
0#
b101 "
b1 !
$end
#10
1+
#20
0+
#30
b1 3
b1 X
b110 "
b110 .
b110 G
b110 ^
b11 !
b11 -
b11 F
b11 _
1#
1+
#40
0+
#50
b10 X
1C
b10 H
b10 O
b10 K
b10 Q
b11 $
b11 I
b10000000 L
0@
b0 P
b1 V
0:
1<
1;
b1 W
b10 M
b10 3
b11 %
b11 2
b11 \
b1 0
b1 Z
1+
#60
0+
#70
b10 X
b10 H
b1 O
b10 K
1B
1)
b10000 L
0?
b1 Q
b10 $
b10 I
09
b10 V
1@
1:
b10 W
b1 M
1*
b10 %
b10 2
b10 \
b10 Z
b10 0
1+
#80
0+
#90
1+
#100
0+
#110
b11 X
b11 H
b11 K
b1 P
b11000 L
0)
17
06
b11 V
1=
b11 S
b11111 T
b1111111110 N
b11 3
0*
b1 ,
b1 /
b1 Y
b1 ]
1+
#120
0+
#130
b11 X
b11 K
b11 H
b1 Q
1C
1A
b11 L
b1 O
0>
0B
b11 U
08
1?
19
b11 W
b0 M
b11 0
b11 Z
b111 "
b111 .
b111 G
b111 ^
b10 !
b10 -
b10 F
b10 _
1+
#140
0+
#150
1+
#160
0+
#170
1+
#180
0+
#190
b1 X
b1 H
b1 K
b0 Q
b1 L
b1 U
b1 W
b1 3
1(
1+
#200
0+
#210
b0 P
b10 O
0A
1>
b111 &
b111 J
18
0@
0:
b10 M
b111 '
b111 1
b111 [
b1 0
b1 Z
b10 X
b10 H
b10 K
b10 Q
b10000000 L
b1 U
b1 W
b10 3
0(
1+
#220
0+
#230
b11 X
b1 P
b11 H
b1 O
b11 K
1B
b11000 L
0?
b1 Q
b110 &
b110 J
09
b10 U
1@
1:
b10 W
b1 M
b11 3
b110 '
b110 1
b110 [
b10 Z
b10 0
1+
#240
0+
#250
b11 X
b11 K
b11 H
b1 Q
1C
1A
b11 L
b1 O
0>
0B
b11 U
08
1?
19
b11 W
b0 M
b11 0
b11 Z
1+
